{"dependencies":[{"name":"/Users/cristobalvalenzuela/dropbox/itp/spring2018/interactivemusic/work/sidewalk/.babelrc","includedInParent":true,"mtime":1520315592761},{"name":"/Users/cristobalvalenzuela/dropbox/itp/spring2018/interactivemusic/work/sidewalk/package.json","includedInParent":true,"mtime":1520326924636},{"name":"./constants","loc":{"line":10,"column":7}},{"name":"./SocketManager","loc":{"line":12,"column":26}},{"name":"./Triggers","loc":{"line":13,"column":21}},{"name":"./Player","loc":{"line":14,"column":33}},{"name":"./video/street01.mp4","loc":{"line":16,"column":20}},{"name":"./video/nyc.mp4","loc":{"line":17,"column":20}},{"name":"./video/street03.mp4","loc":{"line":18,"column":20}}],"generated":{"js":"'use strict';\n\nObject.defineProperty(exports, \"__esModule\", {\n  value: true\n});\nexports.changeSound = exports.changeVideo = exports.trackVideo = exports.isTracking = exports.showRawVideo = exports.triggers = undefined;\n\nvar _constants = require('./constants');\n\nvar _SocketManager = require('./SocketManager');\n\nvar _SocketManager2 = _interopRequireDefault(_SocketManager);\n\nvar _Triggers = require('./Triggers');\n\nvar _Triggers2 = _interopRequireDefault(_Triggers);\n\nvar _Player = require('./Player');\n\nvar _street = require('./video/street01.mp4');\n\nvar _street2 = _interopRequireDefault(_street);\n\nvar _nyc = require('./video/nyc.mp4');\n\nvar _nyc2 = _interopRequireDefault(_nyc);\n\nvar _street3 = require('./video/street03.mp4');\n\nvar _street4 = _interopRequireDefault(_street3);\n\nfunction _interopRequireDefault(obj) { return obj && obj.__esModule ? obj : { default: obj }; }\n\nvar avaiVideos = [_street2.default, _nyc2.default, _street4.default];\n\n// Current color\nvar currentColor = 'rgba(37,255,245, 0.75)';\n// Current selected sound\nvar currentSound = 'soundsA';\n\n// Circle Trigger Manager\nvar triggers = exports.triggers = new _Triggers2.default();\n\nvar humans = [];\nvar capture = void 0;\nvar canvas = void 0;\nvar canvas2Send = void 0;\nvar colors = void 0;\nvar socketManager = void 0;\nvar triggerTracking = false;\n\nvar setup = function setup() {\n  // Canvases\n  canvas = createCanvas(windowWidth, windowHeight);\n  canvas2Send = createGraphics(_constants.IMAGE_WIDTH, _constants.IMAGE_HEIGHT);\n\n  // Live Stream\n  // capture = createCapture(VIDEO);\n\n  // Video Demo\n  capture = createVideo([_nyc2.default]);\n\n  // Socket Manager\n  socketManager = new _SocketManager2.default('http://localhost:33000/query', capture, canvas2Send);\n\n  capture.size(_constants.IMAGE_WIDTH, _constants.IMAGE_HEIGHT);\n  capture.hide();\n  strokeWeight(4);\n  colors = _constants.COLORS.map(function (e) {\n    return color(e);\n  });\n  frameRate(10);\n};\n\nvar draw = function draw() {\n  //image(capture, 0, 0, windowWidth, windowHeight);\n  if (playVideo && !isTracking) {\n    image(capture, 0, 0, windowWidth, windowHeight);\n  }\n\n  noStroke();\n  fill(currentColor);\n\n  // Draw all triggers\n  triggers.getAll().forEach(function (trigger) {\n    return ellipse(trigger.x, trigger.y, _constants.C_SIZE);\n  });\n\n  // Debug sounds with mouse\n  checkAndTriggerSound(mouseX, mouseY, mouseX, mouseY);\n};\n\n// Draw a human\nvar drawHuman = function drawHuman(human) {\n  _constants.BODY_CONNECTIONS.forEach(function (connection, i) {\n    var start = null;\n    var end = null;\n    human.forEach(function (bodyPart) {\n      var name = bodyPart[0];\n      if (name === connection[0]) {\n        start = bodyPart;\n      } else if (name === connection[1]) {\n        end = bodyPart;\n      }\n    });\n    stroke('rgba(87,255,245, 0.75)');\n    if (start && end) {\n      var x1 = start[1] * windowWidth;\n      var y1 = start[2] * windowHeight;\n      var x2 = end[1] * windowWidth;\n      var y2 = end[2] * windowHeight;\n\n      checkAndTriggerSound(x1, y1, x2, y2);\n      line(x1, y1, x2, y2);\n    }\n  });\n};\n\n// Add a new instrument\nvar mousePressed = function mousePressed() {\n  // Check if it's on top of an existing trigger\n  var existing = checkIfOverTrigger(mouseX, mouseY);\n  if (existing.id) {\n    // Remove the existing one\n    triggers.remove(existing);\n  } else if (mouseY < windowHeight - _constants.FOOTER_HEIGHT) {\n    // Add a new trigger\n    triggers.add({\n      id: Date.now(),\n      x: mouseX,\n      y: mouseY,\n      x1: mouseX - _constants.C_RADIUS,\n      x2: mouseX + _constants.C_RADIUS,\n      y1: mouseY - _constants.C_RADIUS,\n      y2: mouseY + _constants.C_RADIUS,\n      soundType: currentSound\n    });\n  }\n};\n\n// Check if human is over a trigger\nvar checkAndTriggerSound = function checkAndTriggerSound(x1, y1, x2, y2) {\n  triggers.getAll().forEach(function (t) {\n    if (x1 >= t.x1 && x1 <= t.x2 && y1 >= t.y1 && y1 <= t.y2 || x2 >= t.x1 && x2 <= t.x2 && y2 >= t.y1 && y2 <= t.y2) {\n      if (t.soundType === 'soundsA') {\n        var i = Math.floor(map(y1, 0, windowHeight, _Player.soundsA.length - 1, 0));\n        if (_Player.soundsA[i].state === 'stopped') {\n          _Player.soundsA[i].start();\n        }\n      } else if (t.soundType === 'soundsB') {\n        var _i = Math.floor(map(y1, 0, windowHeight, _Player.soundsB.length - 1, 0));\n        if (_Player.soundsB[_i].state === 'stopped') {\n          _Player.soundsB[_i].start();\n        }\n      }\n    }\n  });\n};\n\n// Check if click is over a trigger\nvar checkIfOverTrigger = function checkIfOverTrigger(x, y) {\n  var trigger = {};\n  triggers.getAll().forEach(function (t) {\n    if (x >= t.x1 && x <= t.x2 && y >= t.y1 && y <= t.y2) {\n      trigger = t;\n    }\n  });\n  return trigger;\n};\n\nvar playVideo = false;\n// Show the raw video stream\nvar showRawVideo = exports.showRawVideo = function showRawVideo() {\n  playVideo = !playVideo;\n  if (playVideo) {\n    capture.loop();\n  } else {\n    capture.pause();\n  }\n};\n\nvar isTracking = exports.isTracking = false;\n// Start Tracking the current video\nvar trackVideo = exports.trackVideo = function trackVideo() {\n  exports.isTracking = isTracking = !isTracking;\n  if (isTracking) {\n    start();\n  }\n};\n\n// Log start\nvar start = function start() {\n  socketManager.sendImg(canvas2Send.elt.toDataURL(), capture, canvas2Send);\n};\n\n// Change the video src\nvar changeVideo = exports.changeVideo = function changeVideo() {\n  var video = avaiVideos[Math.floor(random(0, avaiVideos.length))];\n  capture.elt.src = video;\n};\n\n// Change the sound and color\nvar changeSound = exports.changeSound = function changeSound(type) {\n  currentSound = type;\n};\n\nwindow.setup = setup;\nwindow.draw = draw;\nwindow.capture = capture;\nwindow.drawHuman = drawHuman;\nwindow.mousePressed = mousePressed;\nwindow.start = start;","map":{"mappings":[{"generated":{"line":8,"column":0},"source":"src/Sketch.js","original":{"line":1,"column":0}},{"generated":{"line":10,"column":0},"source":"src/Sketch.js","original":{"line":12,"column":0}},{"generated":{"line":14,"column":0},"source":"src/Sketch.js","original":{"line":13,"column":0}},{"generated":{"line":18,"column":0},"source":"src/Sketch.js","original":{"line":14,"column":0}},{"generated":{"line":20,"column":0},"source":"src/Sketch.js","original":{"line":16,"column":0}},{"generated":{"line":24,"column":0},"source":"src/Sketch.js","original":{"line":17,"column":0}},{"generated":{"line":28,"column":0},"source":"src/Sketch.js","original":{"line":18,"column":0}},{"generated":{"line":34,"column":0},"source":"src/Sketch.js","original":{"line":20,"column":0}},{"name":"avaiVideos","generated":{"line":34,"column":4},"source":"src/Sketch.js","original":{"line":20,"column":6}},{"generated":{"line":34,"column":17},"source":"src/Sketch.js","original":{"line":20,"column":19}},{"generated":{"line":34,"column":68},"source":"src/Sketch.js","original":{"line":20,"column":0}},{"generated":{"line":36,"column":0},"source":"src/Sketch.js","original":{"line":22,"column":0}},{"generated":{"line":37,"column":0},"source":"src/Sketch.js","original":{"line":23,"column":0}},{"name":"currentColor","generated":{"line":37,"column":4},"source":"src/Sketch.js","original":{"line":23,"column":4}},{"generated":{"line":37,"column":19},"source":"src/Sketch.js","original":{"line":23,"column":19}},{"generated":{"line":37,"column":43},"source":"src/Sketch.js","original":{"line":23,"column":0}},{"generated":{"line":38,"column":0},"source":"src/Sketch.js","original":{"line":24,"column":0}},{"generated":{"line":39,"column":0},"source":"src/Sketch.js","original":{"line":25,"column":0}},{"name":"currentSound","generated":{"line":39,"column":4},"source":"src/Sketch.js","original":{"line":25,"column":4}},{"generated":{"line":39,"column":19},"source":"src/Sketch.js","original":{"line":25,"column":19}},{"generated":{"line":39,"column":28},"source":"src/Sketch.js","original":{"line":25,"column":0}},{"generated":{"line":41,"column":0},"source":"src/Sketch.js","original":{"line":27,"column":0}},{"generated":{"line":42,"column":0},"source":"src/Sketch.js","original":{"line":28,"column":7}},{"name":"triggers","generated":{"line":42,"column":4},"source":"src/Sketch.js","original":{"line":28,"column":13}},{"generated":{"line":42,"column":34},"source":"src/Sketch.js","original":{"line":28,"column":24}},{"generated":{"line":42,"column":58},"source":"src/Sketch.js","original":{"line":28,"column":7}},{"generated":{"line":44,"column":0},"source":"src/Sketch.js","original":{"line":30,"column":0}},{"name":"humans","generated":{"line":44,"column":4},"source":"src/Sketch.js","original":{"line":30,"column":4}},{"generated":{"line":44,"column":13},"source":"src/Sketch.js","original":{"line":30,"column":13}},{"generated":{"line":44,"column":15},"source":"src/Sketch.js","original":{"line":30,"column":0}},{"generated":{"line":45,"column":0},"source":"src/Sketch.js","original":{"line":31,"column":0}},{"name":"capture","generated":{"line":45,"column":4},"source":"src/Sketch.js","original":{"line":31,"column":4}},{"generated":{"line":45,"column":20},"source":"src/Sketch.js","original":{"line":31,"column":0}},{"generated":{"line":46,"column":0},"source":"src/Sketch.js","original":{"line":32,"column":0}},{"name":"canvas","generated":{"line":46,"column":4},"source":"src/Sketch.js","original":{"line":32,"column":4}},{"generated":{"line":46,"column":19},"source":"src/Sketch.js","original":{"line":32,"column":0}},{"generated":{"line":47,"column":0},"source":"src/Sketch.js","original":{"line":33,"column":0}},{"name":"canvas2Send","generated":{"line":47,"column":4},"source":"src/Sketch.js","original":{"line":33,"column":4}},{"generated":{"line":47,"column":24},"source":"src/Sketch.js","original":{"line":33,"column":0}},{"generated":{"line":48,"column":0},"source":"src/Sketch.js","original":{"line":34,"column":0}},{"name":"colors","generated":{"line":48,"column":4},"source":"src/Sketch.js","original":{"line":34,"column":4}},{"generated":{"line":48,"column":19},"source":"src/Sketch.js","original":{"line":34,"column":0}},{"generated":{"line":49,"column":0},"source":"src/Sketch.js","original":{"line":35,"column":0}},{"name":"socketManager","generated":{"line":49,"column":4},"source":"src/Sketch.js","original":{"line":35,"column":4}},{"generated":{"line":49,"column":26},"source":"src/Sketch.js","original":{"line":35,"column":0}},{"generated":{"line":50,"column":0},"source":"src/Sketch.js","original":{"line":36,"column":0}},{"name":"triggerTracking","generated":{"line":50,"column":4},"source":"src/Sketch.js","original":{"line":36,"column":4}},{"generated":{"line":50,"column":22},"source":"src/Sketch.js","original":{"line":36,"column":22}},{"generated":{"line":50,"column":27},"source":"src/Sketch.js","original":{"line":36,"column":0}},{"generated":{"line":52,"column":0},"source":"src/Sketch.js","original":{"line":38,"column":0}},{"name":"setup","generated":{"line":52,"column":4},"source":"src/Sketch.js","original":{"line":38,"column":6}},{"generated":{"line":52,"column":12},"source":"src/Sketch.js","original":{"line":38,"column":14}},{"name":"setup","generated":{"line":52,"column":21},"source":"src/Sketch.js","original":{"line":38,"column":6}},{"generated":{"line":52,"column":26},"source":"src/Sketch.js","original":{"line":38,"column":14}},{"generated":{"line":52,"column":29},"source":"src/Sketch.js","original":{"line":38,"column":20}},{"generated":{"line":53,"column":0},"source":"src/Sketch.js","original":{"line":39,"column":2}},{"name":"canvas","generated":{"line":54,"column":0},"source":"src/Sketch.js","original":{"line":40,"column":2}},{"name":"createCanvas","generated":{"line":54,"column":11},"source":"src/Sketch.js","original":{"line":40,"column":11}},{"name":"windowWidth","generated":{"line":54,"column":24},"source":"src/Sketch.js","original":{"line":40,"column":24}},{"generated":{"line":54,"column":35},"source":"src/Sketch.js","original":{"line":40,"column":11}},{"name":"windowHeight","generated":{"line":54,"column":37},"source":"src/Sketch.js","original":{"line":40,"column":37}},{"generated":{"line":54,"column":49},"source":"src/Sketch.js","original":{"line":40,"column":11}},{"generated":{"line":54,"column":50},"source":"src/Sketch.js","original":{"line":40,"column":2}},{"name":"canvas2Send","generated":{"line":55,"column":0},"source":"src/Sketch.js","original":{"line":41,"column":2}},{"name":"createGraphics","generated":{"line":55,"column":16},"source":"src/Sketch.js","original":{"line":41,"column":16}},{"generated":{"line":55,"column":79},"source":"src/Sketch.js","original":{"line":41,"column":2}},{"generated":{"line":57,"column":0},"source":"src/Sketch.js","original":{"line":43,"column":2}},{"generated":{"line":58,"column":0},"source":"src/Sketch.js","original":{"line":44,"column":2}},{"generated":{"line":60,"column":0},"source":"src/Sketch.js","original":{"line":46,"column":2}},{"name":"capture","generated":{"line":61,"column":0},"source":"src/Sketch.js","original":{"line":47,"column":2}},{"name":"createVideo","generated":{"line":61,"column":12},"source":"src/Sketch.js","original":{"line":47,"column":12}},{"generated":{"line":61,"column":24},"source":"src/Sketch.js","original":{"line":47,"column":24}},{"generated":{"line":61,"column":39},"source":"src/Sketch.js","original":{"line":47,"column":12}},{"generated":{"line":61,"column":40},"source":"src/Sketch.js","original":{"line":47,"column":2}},{"generated":{"line":63,"column":0},"source":"src/Sketch.js","original":{"line":49,"column":2}},{"name":"socketManager","generated":{"line":64,"column":0},"source":"src/Sketch.js","original":{"line":50,"column":2}},{"generated":{"line":64,"column":18},"source":"src/Sketch.js","original":{"line":50,"column":18}},{"generated":{"line":64,"column":46},"source":"src/Sketch.js","original":{"line":50,"column":36}},{"generated":{"line":64,"column":76},"source":"src/Sketch.js","original":{"line":50,"column":18}},{"name":"capture","generated":{"line":64,"column":78},"source":"src/Sketch.js","original":{"line":50,"column":68}},{"generated":{"line":64,"column":85},"source":"src/Sketch.js","original":{"line":50,"column":18}},{"name":"canvas2Send","generated":{"line":64,"column":87},"source":"src/Sketch.js","original":{"line":50,"column":77}},{"generated":{"line":64,"column":98},"source":"src/Sketch.js","original":{"line":50,"column":18}},{"generated":{"line":64,"column":99},"source":"src/Sketch.js","original":{"line":50,"column":2}},{"name":"capture","generated":{"line":66,"column":0},"source":"src/Sketch.js","original":{"line":52,"column":2}},{"name":"size","generated":{"line":66,"column":10},"source":"src/Sketch.js","original":{"line":52,"column":10}},{"generated":{"line":66,"column":14},"source":"src/Sketch.js","original":{"line":52,"column":2}},{"name":"capture","generated":{"line":67,"column":0},"source":"src/Sketch.js","original":{"line":53,"column":2}},{"name":"hide","generated":{"line":67,"column":10},"source":"src/Sketch.js","original":{"line":53,"column":10}},{"generated":{"line":67,"column":14},"source":"src/Sketch.js","original":{"line":53,"column":2}},{"name":"strokeWeight","generated":{"line":68,"column":0},"source":"src/Sketch.js","original":{"line":54,"column":2}},{"generated":{"line":68,"column":15},"source":"src/Sketch.js","original":{"line":54,"column":15}},{"generated":{"line":68,"column":16},"source":"src/Sketch.js","original":{"line":54,"column":2}},{"name":"colors","generated":{"line":69,"column":0},"source":"src/Sketch.js","original":{"line":55,"column":2}},{"generated":{"line":69,"column":11},"source":"src/Sketch.js","original":{"line":55,"column":11}},{"name":"map","generated":{"line":69,"column":29},"source":"src/Sketch.js","original":{"line":55,"column":18}},{"generated":{"line":69,"column":32},"source":"src/Sketch.js","original":{"line":55,"column":11}},{"generated":{"line":69,"column":33},"source":"src/Sketch.js","original":{"line":55,"column":22}},{"generated":{"line":70,"column":0},"source":"src/Sketch.js","original":{"line":55,"column":22}},{"name":"color","generated":{"line":70,"column":11},"source":"src/Sketch.js","original":{"line":55,"column":27}},{"name":"e","generated":{"line":70,"column":17},"source":"src/Sketch.js","original":{"line":55,"column":33}},{"generated":{"line":70,"column":18},"source":"src/Sketch.js","original":{"line":55,"column":27}},{"generated":{"line":70,"column":19},"source":"src/Sketch.js","original":{"line":55,"column":22}},{"generated":{"line":71,"column":0},"source":"src/Sketch.js","original":{"line":55,"column":22}},{"generated":{"line":71,"column":3},"source":"src/Sketch.js","original":{"line":55,"column":11}},{"generated":{"line":71,"column":4},"source":"src/Sketch.js","original":{"line":55,"column":2}},{"name":"frameRate","generated":{"line":72,"column":0},"source":"src/Sketch.js","original":{"line":56,"column":2}},{"generated":{"line":72,"column":12},"source":"src/Sketch.js","original":{"line":56,"column":12}},{"generated":{"line":72,"column":14},"source":"src/Sketch.js","original":{"line":56,"column":2}},{"generated":{"line":73,"column":0},"source":"src/Sketch.js","original":{"line":57,"column":1}},{"generated":{"line":73,"column":1},"source":"src/Sketch.js","original":{"line":38,"column":0}},{"generated":{"line":75,"column":0},"source":"src/Sketch.js","original":{"line":59,"column":0}},{"name":"draw","generated":{"line":75,"column":4},"source":"src/Sketch.js","original":{"line":59,"column":6}},{"generated":{"line":75,"column":11},"source":"src/Sketch.js","original":{"line":59,"column":13}},{"name":"draw","generated":{"line":75,"column":20},"source":"src/Sketch.js","original":{"line":59,"column":6}},{"generated":{"line":75,"column":24},"source":"src/Sketch.js","original":{"line":59,"column":13}},{"generated":{"line":75,"column":27},"source":"src/Sketch.js","original":{"line":59,"column":19}},{"generated":{"line":76,"column":0},"source":"src/Sketch.js","original":{"line":60,"column":2}},{"generated":{"line":77,"column":0},"source":"src/Sketch.js","original":{"line":61,"column":2}},{"name":"playVideo","generated":{"line":77,"column":6},"source":"src/Sketch.js","original":{"line":61,"column":6}},{"generated":{"line":77,"column":19},"source":"src/Sketch.js","original":{"line":61,"column":19}},{"name":"isTracking","generated":{"line":77,"column":20},"source":"src/Sketch.js","original":{"line":61,"column":20}},{"generated":{"line":77,"column":30},"source":"src/Sketch.js","original":{"line":61,"column":2}},{"generated":{"line":77,"column":32},"source":"src/Sketch.js","original":{"line":61,"column":32}},{"name":"image","generated":{"line":78,"column":0},"source":"src/Sketch.js","original":{"line":62,"column":4}},{"name":"capture","generated":{"line":78,"column":10},"source":"src/Sketch.js","original":{"line":62,"column":10}},{"generated":{"line":78,"column":17},"source":"src/Sketch.js","original":{"line":62,"column":4}},{"generated":{"line":78,"column":19},"source":"src/Sketch.js","original":{"line":62,"column":19}},{"generated":{"line":78,"column":20},"source":"src/Sketch.js","original":{"line":62,"column":4}},{"generated":{"line":78,"column":22},"source":"src/Sketch.js","original":{"line":62,"column":22}},{"generated":{"line":78,"column":23},"source":"src/Sketch.js","original":{"line":62,"column":4}},{"name":"windowWidth","generated":{"line":78,"column":25},"source":"src/Sketch.js","original":{"line":62,"column":25}},{"generated":{"line":78,"column":36},"source":"src/Sketch.js","original":{"line":62,"column":4}},{"name":"windowHeight","generated":{"line":78,"column":38},"source":"src/Sketch.js","original":{"line":62,"column":38}},{"generated":{"line":78,"column":50},"source":"src/Sketch.js","original":{"line":62,"column":4}},{"generated":{"line":79,"column":0},"source":"src/Sketch.js","original":{"line":63,"column":3}},{"name":"noStroke","generated":{"line":81,"column":0},"source":"src/Sketch.js","original":{"line":65,"column":2}},{"name":"fill","generated":{"line":82,"column":0},"source":"src/Sketch.js","original":{"line":66,"column":2}},{"name":"currentColor","generated":{"line":82,"column":7},"source":"src/Sketch.js","original":{"line":66,"column":7}},{"generated":{"line":82,"column":19},"source":"src/Sketch.js","original":{"line":66,"column":2}},{"generated":{"line":84,"column":0},"source":"src/Sketch.js","original":{"line":68,"column":2}},{"name":"triggers","generated":{"line":85,"column":0},"source":"src/Sketch.js","original":{"line":69,"column":2}},{"name":"getAll","generated":{"line":85,"column":11},"source":"src/Sketch.js","original":{"line":69,"column":11}},{"generated":{"line":85,"column":17},"source":"src/Sketch.js","original":{"line":69,"column":2}},{"name":"forEach","generated":{"line":85,"column":20},"source":"src/Sketch.js","original":{"line":69,"column":20}},{"generated":{"line":85,"column":27},"source":"src/Sketch.js","original":{"line":69,"column":2}},{"generated":{"line":85,"column":28},"source":"src/Sketch.js","original":{"line":69,"column":28}},{"generated":{"line":86,"column":0},"source":"src/Sketch.js","original":{"line":69,"column":28}},{"name":"ellipse","generated":{"line":86,"column":11},"source":"src/Sketch.js","original":{"line":69,"column":39}},{"name":"trigger","generated":{"line":86,"column":19},"source":"src/Sketch.js","original":{"line":69,"column":47}},{"name":"x","generated":{"line":86,"column":27},"source":"src/Sketch.js","original":{"line":69,"column":55}},{"generated":{"line":86,"column":28},"source":"src/Sketch.js","original":{"line":69,"column":39}},{"name":"trigger","generated":{"line":86,"column":30},"source":"src/Sketch.js","original":{"line":69,"column":58}},{"name":"y","generated":{"line":86,"column":38},"source":"src/Sketch.js","original":{"line":69,"column":66}},{"generated":{"line":86,"column":39},"source":"src/Sketch.js","original":{"line":69,"column":39}},{"generated":{"line":86,"column":59},"source":"src/Sketch.js","original":{"line":69,"column":28}},{"generated":{"line":87,"column":0},"source":"src/Sketch.js","original":{"line":69,"column":28}},{"generated":{"line":87,"column":3},"source":"src/Sketch.js","original":{"line":69,"column":2}},{"generated":{"line":89,"column":0},"source":"src/Sketch.js","original":{"line":71,"column":2}},{"name":"checkAndTriggerSound","generated":{"line":90,"column":0},"source":"src/Sketch.js","original":{"line":72,"column":2}},{"name":"mouseX","generated":{"line":90,"column":23},"source":"src/Sketch.js","original":{"line":72,"column":23}},{"generated":{"line":90,"column":29},"source":"src/Sketch.js","original":{"line":72,"column":2}},{"name":"mouseY","generated":{"line":90,"column":31},"source":"src/Sketch.js","original":{"line":72,"column":31}},{"generated":{"line":90,"column":37},"source":"src/Sketch.js","original":{"line":72,"column":2}},{"name":"mouseX","generated":{"line":90,"column":39},"source":"src/Sketch.js","original":{"line":72,"column":39}},{"generated":{"line":90,"column":45},"source":"src/Sketch.js","original":{"line":72,"column":2}},{"name":"mouseY","generated":{"line":90,"column":47},"source":"src/Sketch.js","original":{"line":72,"column":47}},{"generated":{"line":90,"column":53},"source":"src/Sketch.js","original":{"line":72,"column":2}},{"generated":{"line":91,"column":0},"source":"src/Sketch.js","original":{"line":73,"column":1}},{"generated":{"line":91,"column":1},"source":"src/Sketch.js","original":{"line":59,"column":0}},{"generated":{"line":93,"column":0},"source":"src/Sketch.js","original":{"line":75,"column":0}},{"generated":{"line":94,"column":0},"source":"src/Sketch.js","original":{"line":76,"column":0}},{"name":"drawHuman","generated":{"line":94,"column":4},"source":"src/Sketch.js","original":{"line":76,"column":6}},{"generated":{"line":94,"column":16},"source":"src/Sketch.js","original":{"line":76,"column":18}},{"name":"drawHuman","generated":{"line":94,"column":25},"source":"src/Sketch.js","original":{"line":76,"column":6}},{"generated":{"line":94,"column":34},"source":"src/Sketch.js","original":{"line":76,"column":18}},{"name":"human","generated":{"line":94,"column":35},"source":"src/Sketch.js","original":{"line":76,"column":19}},{"generated":{"line":94,"column":40},"source":"src/Sketch.js","original":{"line":76,"column":18}},{"generated":{"line":94,"column":42},"source":"src/Sketch.js","original":{"line":76,"column":29}},{"generated":{"line":95,"column":0},"source":"src/Sketch.js","original":{"line":77,"column":2}},{"name":"forEach","generated":{"line":95,"column":30},"source":"src/Sketch.js","original":{"line":77,"column":19}},{"generated":{"line":95,"column":37},"source":"src/Sketch.js","original":{"line":77,"column":2}},{"generated":{"line":95,"column":38},"source":"src/Sketch.js","original":{"line":77,"column":27}},{"name":"connection","generated":{"line":95,"column":48},"source":"src/Sketch.js","original":{"line":77,"column":28}},{"generated":{"line":95,"column":58},"source":"src/Sketch.js","original":{"line":77,"column":27}},{"name":"i","generated":{"line":95,"column":60},"source":"src/Sketch.js","original":{"line":77,"column":40}},{"generated":{"line":95,"column":61},"source":"src/Sketch.js","original":{"line":77,"column":27}},{"generated":{"line":95,"column":63},"source":"src/Sketch.js","original":{"line":77,"column":46}},{"generated":{"line":96,"column":0},"source":"src/Sketch.js","original":{"line":78,"column":4}},{"name":"start","generated":{"line":96,"column":8},"source":"src/Sketch.js","original":{"line":78,"column":8}},{"generated":{"line":96,"column":16},"source":"src/Sketch.js","original":{"line":78,"column":16}},{"generated":{"line":96,"column":20},"source":"src/Sketch.js","original":{"line":78,"column":4}},{"generated":{"line":97,"column":0},"source":"src/Sketch.js","original":{"line":79,"column":4}},{"name":"end","generated":{"line":97,"column":8},"source":"src/Sketch.js","original":{"line":79,"column":8}},{"generated":{"line":97,"column":14},"source":"src/Sketch.js","original":{"line":79,"column":14}},{"generated":{"line":97,"column":18},"source":"src/Sketch.js","original":{"line":79,"column":4}},{"name":"human","generated":{"line":98,"column":0},"source":"src/Sketch.js","original":{"line":80,"column":4}},{"name":"forEach","generated":{"line":98,"column":10},"source":"src/Sketch.js","original":{"line":80,"column":10}},{"generated":{"line":98,"column":17},"source":"src/Sketch.js","original":{"line":80,"column":4}},{"generated":{"line":98,"column":18},"source":"src/Sketch.js","original":{"line":80,"column":18}},{"generated":{"line":98,"column":38},"source":"src/Sketch.js","original":{"line":80,"column":30}},{"generated":{"line":99,"column":0},"source":"src/Sketch.js","original":{"line":81,"column":6}},{"name":"name","generated":{"line":99,"column":10},"source":"src/Sketch.js","original":{"line":81,"column":12}},{"name":"bodyPart","generated":{"line":99,"column":17},"source":"src/Sketch.js","original":{"line":81,"column":19}},{"generated":{"line":99,"column":26},"source":"src/Sketch.js","original":{"line":81,"column":28}},{"generated":{"line":99,"column":27},"source":"src/Sketch.js","original":{"line":81,"column":19}},{"generated":{"line":99,"column":28},"source":"src/Sketch.js","original":{"line":81,"column":6}},{"generated":{"line":100,"column":0},"source":"src/Sketch.js","original":{"line":82,"column":6}},{"name":"name","generated":{"line":100,"column":10},"source":"src/Sketch.js","original":{"line":82,"column":10}},{"name":"connection","generated":{"line":100,"column":19},"source":"src/Sketch.js","original":{"line":82,"column":19}},{"generated":{"line":100,"column":30},"source":"src/Sketch.js","original":{"line":82,"column":30}},{"generated":{"line":100,"column":31},"source":"src/Sketch.js","original":{"line":82,"column":19}},{"generated":{"line":100,"column":32},"source":"src/Sketch.js","original":{"line":82,"column":6}},{"generated":{"line":100,"column":34},"source":"src/Sketch.js","original":{"line":82,"column":34}},{"name":"start","generated":{"line":101,"column":0},"source":"src/Sketch.js","original":{"line":83,"column":8}},{"name":"bodyPart","generated":{"line":101,"column":16},"source":"src/Sketch.js","original":{"line":83,"column":16}},{"generated":{"line":101,"column":24},"source":"src/Sketch.js","original":{"line":83,"column":8}},{"generated":{"line":102,"column":0},"source":"src/Sketch.js","original":{"line":84,"column":7}},{"generated":{"line":102,"column":7},"source":"src/Sketch.js","original":{"line":82,"column":6}},{"generated":{"line":102,"column":13},"source":"src/Sketch.js","original":{"line":84,"column":13}},{"name":"name","generated":{"line":102,"column":17},"source":"src/Sketch.js","original":{"line":84,"column":17}},{"name":"connection","generated":{"line":102,"column":26},"source":"src/Sketch.js","original":{"line":84,"column":26}},{"generated":{"line":102,"column":37},"source":"src/Sketch.js","original":{"line":84,"column":37}},{"generated":{"line":102,"column":38},"source":"src/Sketch.js","original":{"line":84,"column":26}},{"generated":{"line":102,"column":39},"source":"src/Sketch.js","original":{"line":84,"column":13}},{"generated":{"line":102,"column":41},"source":"src/Sketch.js","original":{"line":84,"column":41}},{"name":"end","generated":{"line":103,"column":0},"source":"src/Sketch.js","original":{"line":85,"column":8}},{"name":"bodyPart","generated":{"line":103,"column":14},"source":"src/Sketch.js","original":{"line":85,"column":14}},{"generated":{"line":103,"column":22},"source":"src/Sketch.js","original":{"line":85,"column":8}},{"generated":{"line":104,"column":0},"source":"src/Sketch.js","original":{"line":86,"column":7}},{"generated":{"line":105,"column":0},"source":"src/Sketch.js","original":{"line":87,"column":5}},{"generated":{"line":105,"column":5},"source":"src/Sketch.js","original":{"line":80,"column":4}},{"name":"stroke","generated":{"line":106,"column":0},"source":"src/Sketch.js","original":{"line":88,"column":4}},{"generated":{"line":106,"column":11},"source":"src/Sketch.js","original":{"line":88,"column":11}},{"generated":{"line":106,"column":35},"source":"src/Sketch.js","original":{"line":88,"column":4}},{"generated":{"line":107,"column":0},"source":"src/Sketch.js","original":{"line":89,"column":4}},{"name":"start","generated":{"line":107,"column":8},"source":"src/Sketch.js","original":{"line":89,"column":8}},{"name":"end","generated":{"line":107,"column":17},"source":"src/Sketch.js","original":{"line":89,"column":17}},{"generated":{"line":107,"column":20},"source":"src/Sketch.js","original":{"line":89,"column":4}},{"generated":{"line":107,"column":22},"source":"src/Sketch.js","original":{"line":89,"column":22}},{"generated":{"line":108,"column":0},"source":"src/Sketch.js","original":{"line":90,"column":6}},{"name":"x1","generated":{"line":108,"column":10},"source":"src/Sketch.js","original":{"line":90,"column":12}},{"name":"start","generated":{"line":108,"column":15},"source":"src/Sketch.js","original":{"line":90,"column":17}},{"generated":{"line":108,"column":21},"source":"src/Sketch.js","original":{"line":90,"column":23}},{"generated":{"line":108,"column":22},"source":"src/Sketch.js","original":{"line":90,"column":17}},{"name":"windowWidth","generated":{"line":108,"column":26},"source":"src/Sketch.js","original":{"line":90,"column":28}},{"generated":{"line":108,"column":37},"source":"src/Sketch.js","original":{"line":90,"column":6}},{"generated":{"line":109,"column":0},"source":"src/Sketch.js","original":{"line":91,"column":6}},{"name":"y1","generated":{"line":109,"column":10},"source":"src/Sketch.js","original":{"line":91,"column":12}},{"name":"start","generated":{"line":109,"column":15},"source":"src/Sketch.js","original":{"line":91,"column":17}},{"generated":{"line":109,"column":21},"source":"src/Sketch.js","original":{"line":91,"column":23}},{"generated":{"line":109,"column":22},"source":"src/Sketch.js","original":{"line":91,"column":17}},{"name":"windowHeight","generated":{"line":109,"column":26},"source":"src/Sketch.js","original":{"line":91,"column":28}},{"generated":{"line":109,"column":38},"source":"src/Sketch.js","original":{"line":91,"column":6}},{"generated":{"line":110,"column":0},"source":"src/Sketch.js","original":{"line":92,"column":6}},{"name":"x2","generated":{"line":110,"column":10},"source":"src/Sketch.js","original":{"line":92,"column":12}},{"name":"end","generated":{"line":110,"column":15},"source":"src/Sketch.js","original":{"line":92,"column":17}},{"generated":{"line":110,"column":19},"source":"src/Sketch.js","original":{"line":92,"column":21}},{"generated":{"line":110,"column":20},"source":"src/Sketch.js","original":{"line":92,"column":17}},{"name":"windowWidth","generated":{"line":110,"column":24},"source":"src/Sketch.js","original":{"line":92,"column":26}},{"generated":{"line":110,"column":35},"source":"src/Sketch.js","original":{"line":92,"column":6}},{"generated":{"line":111,"column":0},"source":"src/Sketch.js","original":{"line":93,"column":6}},{"name":"y2","generated":{"line":111,"column":10},"source":"src/Sketch.js","original":{"line":93,"column":12}},{"name":"end","generated":{"line":111,"column":15},"source":"src/Sketch.js","original":{"line":93,"column":17}},{"generated":{"line":111,"column":19},"source":"src/Sketch.js","original":{"line":93,"column":21}},{"generated":{"line":111,"column":20},"source":"src/Sketch.js","original":{"line":93,"column":17}},{"name":"windowHeight","generated":{"line":111,"column":24},"source":"src/Sketch.js","original":{"line":93,"column":26}},{"generated":{"line":111,"column":36},"source":"src/Sketch.js","original":{"line":93,"column":6}},{"name":"checkAndTriggerSound","generated":{"line":113,"column":0},"source":"src/Sketch.js","original":{"line":95,"column":6}},{"name":"x1","generated":{"line":113,"column":27},"source":"src/Sketch.js","original":{"line":95,"column":27}},{"generated":{"line":113,"column":29},"source":"src/Sketch.js","original":{"line":95,"column":6}},{"name":"y1","generated":{"line":113,"column":31},"source":"src/Sketch.js","original":{"line":95,"column":31}},{"generated":{"line":113,"column":33},"source":"src/Sketch.js","original":{"line":95,"column":6}},{"name":"x2","generated":{"line":113,"column":35},"source":"src/Sketch.js","original":{"line":95,"column":35}},{"generated":{"line":113,"column":37},"source":"src/Sketch.js","original":{"line":95,"column":6}},{"name":"y2","generated":{"line":113,"column":39},"source":"src/Sketch.js","original":{"line":95,"column":39}},{"generated":{"line":113,"column":41},"source":"src/Sketch.js","original":{"line":95,"column":6}},{"name":"line","generated":{"line":114,"column":0},"source":"src/Sketch.js","original":{"line":96,"column":6}},{"name":"x1","generated":{"line":114,"column":11},"source":"src/Sketch.js","original":{"line":96,"column":11}},{"generated":{"line":114,"column":13},"source":"src/Sketch.js","original":{"line":96,"column":6}},{"name":"y1","generated":{"line":114,"column":15},"source":"src/Sketch.js","original":{"line":96,"column":15}},{"generated":{"line":114,"column":17},"source":"src/Sketch.js","original":{"line":96,"column":6}},{"name":"x2","generated":{"line":114,"column":19},"source":"src/Sketch.js","original":{"line":96,"column":19}},{"generated":{"line":114,"column":21},"source":"src/Sketch.js","original":{"line":96,"column":6}},{"name":"y2","generated":{"line":114,"column":23},"source":"src/Sketch.js","original":{"line":96,"column":23}},{"generated":{"line":114,"column":25},"source":"src/Sketch.js","original":{"line":96,"column":6}},{"generated":{"line":115,"column":0},"source":"src/Sketch.js","original":{"line":97,"column":5}},{"generated":{"line":116,"column":0},"source":"src/Sketch.js","original":{"line":98,"column":3}},{"generated":{"line":116,"column":3},"source":"src/Sketch.js","original":{"line":77,"column":2}},{"generated":{"line":117,"column":0},"source":"src/Sketch.js","original":{"line":99,"column":1}},{"generated":{"line":117,"column":1},"source":"src/Sketch.js","original":{"line":76,"column":0}},{"generated":{"line":119,"column":0},"source":"src/Sketch.js","original":{"line":101,"column":0}},{"generated":{"line":120,"column":0},"source":"src/Sketch.js","original":{"line":102,"column":0}},{"name":"mousePressed","generated":{"line":120,"column":4},"source":"src/Sketch.js","original":{"line":102,"column":6}},{"generated":{"line":120,"column":19},"source":"src/Sketch.js","original":{"line":102,"column":21}},{"name":"mousePressed","generated":{"line":120,"column":28},"source":"src/Sketch.js","original":{"line":102,"column":6}},{"generated":{"line":120,"column":40},"source":"src/Sketch.js","original":{"line":102,"column":21}},{"generated":{"line":120,"column":43},"source":"src/Sketch.js","original":{"line":102,"column":27}},{"generated":{"line":121,"column":0},"source":"src/Sketch.js","original":{"line":103,"column":2}},{"generated":{"line":122,"column":0},"source":"src/Sketch.js","original":{"line":104,"column":2}},{"name":"existing","generated":{"line":122,"column":6},"source":"src/Sketch.js","original":{"line":104,"column":8}},{"name":"checkIfOverTrigger","generated":{"line":122,"column":17},"source":"src/Sketch.js","original":{"line":104,"column":19}},{"name":"mouseX","generated":{"line":122,"column":36},"source":"src/Sketch.js","original":{"line":104,"column":38}},{"generated":{"line":122,"column":42},"source":"src/Sketch.js","original":{"line":104,"column":19}},{"name":"mouseY","generated":{"line":122,"column":44},"source":"src/Sketch.js","original":{"line":104,"column":46}},{"generated":{"line":122,"column":50},"source":"src/Sketch.js","original":{"line":104,"column":19}},{"generated":{"line":122,"column":51},"source":"src/Sketch.js","original":{"line":104,"column":2}},{"generated":{"line":123,"column":0},"source":"src/Sketch.js","original":{"line":105,"column":2}},{"name":"existing","generated":{"line":123,"column":6},"source":"src/Sketch.js","original":{"line":105,"column":6}},{"name":"id","generated":{"line":123,"column":15},"source":"src/Sketch.js","original":{"line":105,"column":15}},{"generated":{"line":123,"column":17},"source":"src/Sketch.js","original":{"line":105,"column":2}},{"generated":{"line":123,"column":19},"source":"src/Sketch.js","original":{"line":105,"column":19}},{"generated":{"line":124,"column":0},"source":"src/Sketch.js","original":{"line":106,"column":4}},{"name":"triggers","generated":{"line":125,"column":0},"source":"src/Sketch.js","original":{"line":107,"column":4}},{"name":"remove","generated":{"line":125,"column":13},"source":"src/Sketch.js","original":{"line":107,"column":13}},{"generated":{"line":125,"column":19},"source":"src/Sketch.js","original":{"line":107,"column":4}},{"name":"existing","generated":{"line":125,"column":20},"source":"src/Sketch.js","original":{"line":107,"column":20}},{"generated":{"line":125,"column":28},"source":"src/Sketch.js","original":{"line":107,"column":4}},{"generated":{"line":126,"column":0},"source":"src/Sketch.js","original":{"line":108,"column":3}},{"generated":{"line":126,"column":3},"source":"src/Sketch.js","original":{"line":105,"column":2}},{"generated":{"line":126,"column":9},"source":"src/Sketch.js","original":{"line":108,"column":9}},{"name":"mouseY","generated":{"line":126,"column":13},"source":"src/Sketch.js","original":{"line":108,"column":12}},{"name":"windowHeight","generated":{"line":126,"column":22},"source":"src/Sketch.js","original":{"line":108,"column":21}},{"generated":{"line":126,"column":61},"source":"src/Sketch.js","original":{"line":108,"column":9}},{"generated":{"line":126,"column":63},"source":"src/Sketch.js","original":{"line":108,"column":51}},{"generated":{"line":127,"column":0},"source":"src/Sketch.js","original":{"line":109,"column":4}},{"name":"triggers","generated":{"line":128,"column":0},"source":"src/Sketch.js","original":{"line":110,"column":4}},{"name":"add","generated":{"line":128,"column":13},"source":"src/Sketch.js","original":{"line":110,"column":13}},{"generated":{"line":128,"column":16},"source":"src/Sketch.js","original":{"line":110,"column":4}},{"generated":{"line":128,"column":17},"source":"src/Sketch.js","original":{"line":110,"column":17}},{"name":"id","generated":{"line":129,"column":0},"source":"src/Sketch.js","original":{"line":111,"column":6}},{"name":"Date","generated":{"line":129,"column":10},"source":"src/Sketch.js","original":{"line":111,"column":10}},{"name":"now","generated":{"line":129,"column":15},"source":"src/Sketch.js","original":{"line":111,"column":15}},{"generated":{"line":129,"column":18},"source":"src/Sketch.js","original":{"line":111,"column":10}},{"generated":{"line":129,"column":20},"source":"src/Sketch.js","original":{"line":110,"column":17}},{"name":"x","generated":{"line":130,"column":0},"source":"src/Sketch.js","original":{"line":112,"column":6}},{"name":"mouseX","generated":{"line":130,"column":9},"source":"src/Sketch.js","original":{"line":112,"column":9}},{"generated":{"line":130,"column":15},"source":"src/Sketch.js","original":{"line":110,"column":17}},{"name":"y","generated":{"line":131,"column":0},"source":"src/Sketch.js","original":{"line":113,"column":6}},{"name":"mouseY","generated":{"line":131,"column":9},"source":"src/Sketch.js","original":{"line":113,"column":9}},{"generated":{"line":131,"column":15},"source":"src/Sketch.js","original":{"line":110,"column":17}},{"name":"x1","generated":{"line":132,"column":0},"source":"src/Sketch.js","original":{"line":114,"column":6}},{"name":"mouseX","generated":{"line":132,"column":10},"source":"src/Sketch.js","original":{"line":114,"column":10}},{"generated":{"line":132,"column":38},"source":"src/Sketch.js","original":{"line":110,"column":17}},{"name":"x2","generated":{"line":133,"column":0},"source":"src/Sketch.js","original":{"line":115,"column":6}},{"name":"mouseX","generated":{"line":133,"column":10},"source":"src/Sketch.js","original":{"line":115,"column":10}},{"generated":{"line":133,"column":38},"source":"src/Sketch.js","original":{"line":110,"column":17}},{"name":"y1","generated":{"line":134,"column":0},"source":"src/Sketch.js","original":{"line":116,"column":6}},{"name":"mouseY","generated":{"line":134,"column":10},"source":"src/Sketch.js","original":{"line":116,"column":10}},{"generated":{"line":134,"column":38},"source":"src/Sketch.js","original":{"line":110,"column":17}},{"name":"y2","generated":{"line":135,"column":0},"source":"src/Sketch.js","original":{"line":117,"column":6}},{"name":"mouseY","generated":{"line":135,"column":10},"source":"src/Sketch.js","original":{"line":117,"column":10}},{"generated":{"line":135,"column":38},"source":"src/Sketch.js","original":{"line":110,"column":17}},{"name":"soundType","generated":{"line":136,"column":0},"source":"src/Sketch.js","original":{"line":118,"column":6}},{"name":"currentSound","generated":{"line":136,"column":17},"source":"src/Sketch.js","original":{"line":118,"column":17}},{"generated":{"line":137,"column":0},"source":"src/Sketch.js","original":{"line":110,"column":17}},{"generated":{"line":137,"column":5},"source":"src/Sketch.js","original":{"line":110,"column":4}},{"generated":{"line":138,"column":0},"source":"src/Sketch.js","original":{"line":120,"column":3}},{"generated":{"line":139,"column":0},"source":"src/Sketch.js","original":{"line":121,"column":1}},{"generated":{"line":139,"column":1},"source":"src/Sketch.js","original":{"line":102,"column":0}},{"generated":{"line":141,"column":0},"source":"src/Sketch.js","original":{"line":123,"column":0}},{"generated":{"line":142,"column":0},"source":"src/Sketch.js","original":{"line":124,"column":0}},{"name":"checkAndTriggerSound","generated":{"line":142,"column":4},"source":"src/Sketch.js","original":{"line":124,"column":6}},{"generated":{"line":142,"column":27},"source":"src/Sketch.js","original":{"line":124,"column":29}},{"name":"checkAndTriggerSound","generated":{"line":142,"column":36},"source":"src/Sketch.js","original":{"line":124,"column":6}},{"generated":{"line":142,"column":56},"source":"src/Sketch.js","original":{"line":124,"column":29}},{"name":"x1","generated":{"line":142,"column":57},"source":"src/Sketch.js","original":{"line":124,"column":30}},{"generated":{"line":142,"column":59},"source":"src/Sketch.js","original":{"line":124,"column":29}},{"name":"y1","generated":{"line":142,"column":61},"source":"src/Sketch.js","original":{"line":124,"column":34}},{"generated":{"line":142,"column":63},"source":"src/Sketch.js","original":{"line":124,"column":29}},{"name":"x2","generated":{"line":142,"column":65},"source":"src/Sketch.js","original":{"line":124,"column":38}},{"generated":{"line":142,"column":67},"source":"src/Sketch.js","original":{"line":124,"column":29}},{"name":"y2","generated":{"line":142,"column":69},"source":"src/Sketch.js","original":{"line":124,"column":42}},{"generated":{"line":142,"column":71},"source":"src/Sketch.js","original":{"line":124,"column":29}},{"generated":{"line":142,"column":73},"source":"src/Sketch.js","original":{"line":124,"column":49}},{"name":"triggers","generated":{"line":143,"column":0},"source":"src/Sketch.js","original":{"line":125,"column":2}},{"name":"getAll","generated":{"line":143,"column":11},"source":"src/Sketch.js","original":{"line":125,"column":11}},{"generated":{"line":143,"column":17},"source":"src/Sketch.js","original":{"line":125,"column":2}},{"name":"forEach","generated":{"line":143,"column":20},"source":"src/Sketch.js","original":{"line":125,"column":20}},{"generated":{"line":143,"column":27},"source":"src/Sketch.js","original":{"line":125,"column":2}},{"generated":{"line":143,"column":28},"source":"src/Sketch.js","original":{"line":125,"column":28}},{"generated":{"line":143,"column":41},"source":"src/Sketch.js","original":{"line":125,"column":33}},{"generated":{"line":144,"column":0},"source":"src/Sketch.js","original":{"line":126,"column":4}},{"name":"x1","generated":{"line":144,"column":8},"source":"src/Sketch.js","original":{"line":126,"column":8}},{"name":"t","generated":{"line":144,"column":14},"source":"src/Sketch.js","original":{"line":126,"column":14}},{"name":"x1","generated":{"line":144,"column":16},"source":"src/Sketch.js","original":{"line":126,"column":16}},{"generated":{"line":144,"column":18},"source":"src/Sketch.js","original":{"line":126,"column":8}},{"name":"x1","generated":{"line":144,"column":22},"source":"src/Sketch.js","original":{"line":126,"column":22}},{"name":"t","generated":{"line":144,"column":28},"source":"src/Sketch.js","original":{"line":126,"column":28}},{"name":"x2","generated":{"line":144,"column":30},"source":"src/Sketch.js","original":{"line":126,"column":30}},{"generated":{"line":144,"column":32},"source":"src/Sketch.js","original":{"line":126,"column":8}},{"name":"y1","generated":{"line":144,"column":36},"source":"src/Sketch.js","original":{"line":126,"column":36}},{"name":"t","generated":{"line":144,"column":42},"source":"src/Sketch.js","original":{"line":126,"column":42}},{"name":"y1","generated":{"line":144,"column":44},"source":"src/Sketch.js","original":{"line":126,"column":44}},{"generated":{"line":144,"column":46},"source":"src/Sketch.js","original":{"line":126,"column":8}},{"name":"y1","generated":{"line":144,"column":50},"source":"src/Sketch.js","original":{"line":126,"column":50}},{"name":"t","generated":{"line":144,"column":56},"source":"src/Sketch.js","original":{"line":126,"column":56}},{"name":"y2","generated":{"line":144,"column":58},"source":"src/Sketch.js","original":{"line":126,"column":58}},{"generated":{"line":144,"column":60},"source":"src/Sketch.js","original":{"line":126,"column":8}},{"name":"x2","generated":{"line":144,"column":64},"source":"src/Sketch.js","original":{"line":126,"column":64}},{"name":"t","generated":{"line":144,"column":70},"source":"src/Sketch.js","original":{"line":126,"column":70}},{"name":"x1","generated":{"line":144,"column":72},"source":"src/Sketch.js","original":{"line":126,"column":72}},{"generated":{"line":144,"column":74},"source":"src/Sketch.js","original":{"line":126,"column":64}},{"name":"x2","generated":{"line":144,"column":78},"source":"src/Sketch.js","original":{"line":126,"column":78}},{"name":"t","generated":{"line":144,"column":84},"source":"src/Sketch.js","original":{"line":126,"column":84}},{"name":"x2","generated":{"line":144,"column":86},"source":"src/Sketch.js","original":{"line":126,"column":86}},{"generated":{"line":144,"column":88},"source":"src/Sketch.js","original":{"line":126,"column":64}},{"name":"y2","generated":{"line":144,"column":92},"source":"src/Sketch.js","original":{"line":126,"column":92}},{"name":"t","generated":{"line":144,"column":98},"source":"src/Sketch.js","original":{"line":126,"column":98}},{"name":"y1","generated":{"line":144,"column":100},"source":"src/Sketch.js","original":{"line":126,"column":100}},{"generated":{"line":144,"column":102},"source":"src/Sketch.js","original":{"line":126,"column":64}},{"name":"y2","generated":{"line":144,"column":106},"source":"src/Sketch.js","original":{"line":126,"column":106}},{"name":"t","generated":{"line":144,"column":112},"source":"src/Sketch.js","original":{"line":126,"column":112}},{"name":"y2","generated":{"line":144,"column":114},"source":"src/Sketch.js","original":{"line":126,"column":114}},{"generated":{"line":144,"column":116},"source":"src/Sketch.js","original":{"line":126,"column":4}},{"generated":{"line":144,"column":118},"source":"src/Sketch.js","original":{"line":126,"column":118}},{"generated":{"line":145,"column":0},"source":"src/Sketch.js","original":{"line":127,"column":6}},{"name":"t","generated":{"line":145,"column":10},"source":"src/Sketch.js","original":{"line":127,"column":9}},{"name":"soundType","generated":{"line":145,"column":12},"source":"src/Sketch.js","original":{"line":127,"column":11}},{"generated":{"line":145,"column":21},"source":"src/Sketch.js","original":{"line":127,"column":9}},{"generated":{"line":145,"column":26},"source":"src/Sketch.js","original":{"line":127,"column":25}},{"generated":{"line":145,"column":35},"source":"src/Sketch.js","original":{"line":127,"column":6}},{"generated":{"line":145,"column":37},"source":"src/Sketch.js","original":{"line":127,"column":35}},{"generated":{"line":146,"column":0},"source":"src/Sketch.js","original":{"line":128,"column":8}},{"name":"i","generated":{"line":146,"column":12},"source":"src/Sketch.js","original":{"line":128,"column":14}},{"name":"Math","generated":{"line":146,"column":16},"source":"src/Sketch.js","original":{"line":128,"column":18}},{"name":"floor","generated":{"line":146,"column":21},"source":"src/Sketch.js","original":{"line":128,"column":23}},{"generated":{"line":146,"column":26},"source":"src/Sketch.js","original":{"line":128,"column":18}},{"name":"map","generated":{"line":146,"column":27},"source":"src/Sketch.js","original":{"line":128,"column":29}},{"name":"y1","generated":{"line":146,"column":31},"source":"src/Sketch.js","original":{"line":128,"column":33}},{"generated":{"line":146,"column":33},"source":"src/Sketch.js","original":{"line":128,"column":29}},{"generated":{"line":146,"column":35},"source":"src/Sketch.js","original":{"line":128,"column":37}},{"generated":{"line":146,"column":36},"source":"src/Sketch.js","original":{"line":128,"column":29}},{"name":"windowHeight","generated":{"line":146,"column":38},"source":"src/Sketch.js","original":{"line":128,"column":40}},{"generated":{"line":146,"column":50},"source":"src/Sketch.js","original":{"line":128,"column":29}},{"generated":{"line":146,"column":52},"source":"src/Sketch.js","original":{"line":128,"column":54}},{"name":"length","generated":{"line":146,"column":68},"source":"src/Sketch.js","original":{"line":128,"column":62}},{"generated":{"line":146,"column":74},"source":"src/Sketch.js","original":{"line":128,"column":54}},{"generated":{"line":146,"column":77},"source":"src/Sketch.js","original":{"line":128,"column":71}},{"generated":{"line":146,"column":78},"source":"src/Sketch.js","original":{"line":128,"column":29}},{"generated":{"line":146,"column":80},"source":"src/Sketch.js","original":{"line":128,"column":74}},{"generated":{"line":146,"column":81},"source":"src/Sketch.js","original":{"line":128,"column":29}},{"generated":{"line":146,"column":82},"source":"src/Sketch.js","original":{"line":128,"column":18}},{"generated":{"line":146,"column":83},"source":"src/Sketch.js","original":{"line":128,"column":8}},{"generated":{"line":147,"column":0},"source":"src/Sketch.js","original":{"line":129,"column":8}},{"generated":{"line":147,"column":12},"source":"src/Sketch.js","original":{"line":129,"column":12}},{"name":"i","generated":{"line":147,"column":28},"source":"src/Sketch.js","original":{"line":129,"column":20}},{"generated":{"line":147,"column":29},"source":"src/Sketch.js","original":{"line":129,"column":12}},{"name":"state","generated":{"line":147,"column":31},"source":"src/Sketch.js","original":{"line":129,"column":23}},{"generated":{"line":147,"column":36},"source":"src/Sketch.js","original":{"line":129,"column":12}},{"generated":{"line":147,"column":41},"source":"src/Sketch.js","original":{"line":129,"column":33}},{"generated":{"line":147,"column":50},"source":"src/Sketch.js","original":{"line":129,"column":8}},{"generated":{"line":147,"column":52},"source":"src/Sketch.js","original":{"line":129,"column":44}},{"generated":{"line":148,"column":0},"source":"src/Sketch.js","original":{"line":130,"column":10}},{"name":"i","generated":{"line":148,"column":26},"source":"src/Sketch.js","original":{"line":130,"column":18}},{"generated":{"line":148,"column":27},"source":"src/Sketch.js","original":{"line":130,"column":10}},{"name":"start","generated":{"line":148,"column":29},"source":"src/Sketch.js","original":{"line":130,"column":21}},{"generated":{"line":148,"column":34},"source":"src/Sketch.js","original":{"line":130,"column":10}},{"generated":{"line":149,"column":0},"source":"src/Sketch.js","original":{"line":131,"column":9}},{"generated":{"line":150,"column":0},"source":"src/Sketch.js","original":{"line":132,"column":7}},{"generated":{"line":150,"column":7},"source":"src/Sketch.js","original":{"line":127,"column":6}},{"generated":{"line":150,"column":13},"source":"src/Sketch.js","original":{"line":132,"column":13}},{"name":"t","generated":{"line":150,"column":17},"source":"src/Sketch.js","original":{"line":132,"column":16}},{"name":"soundType","generated":{"line":150,"column":19},"source":"src/Sketch.js","original":{"line":132,"column":18}},{"generated":{"line":150,"column":28},"source":"src/Sketch.js","original":{"line":132,"column":16}},{"generated":{"line":150,"column":33},"source":"src/Sketch.js","original":{"line":132,"column":32}},{"generated":{"line":150,"column":42},"source":"src/Sketch.js","original":{"line":132,"column":13}},{"generated":{"line":150,"column":44},"source":"src/Sketch.js","original":{"line":132,"column":43}},{"generated":{"line":151,"column":0},"source":"src/Sketch.js","original":{"line":133,"column":8}},{"name":"i","generated":{"line":151,"column":12},"source":"src/Sketch.js","original":{"line":133,"column":14}},{"name":"Math","generated":{"line":151,"column":17},"source":"src/Sketch.js","original":{"line":133,"column":18}},{"name":"floor","generated":{"line":151,"column":22},"source":"src/Sketch.js","original":{"line":133,"column":23}},{"generated":{"line":151,"column":27},"source":"src/Sketch.js","original":{"line":133,"column":18}},{"name":"map","generated":{"line":151,"column":28},"source":"src/Sketch.js","original":{"line":133,"column":29}},{"name":"y1","generated":{"line":151,"column":32},"source":"src/Sketch.js","original":{"line":133,"column":33}},{"generated":{"line":151,"column":34},"source":"src/Sketch.js","original":{"line":133,"column":29}},{"generated":{"line":151,"column":36},"source":"src/Sketch.js","original":{"line":133,"column":37}},{"generated":{"line":151,"column":37},"source":"src/Sketch.js","original":{"line":133,"column":29}},{"name":"windowHeight","generated":{"line":151,"column":39},"source":"src/Sketch.js","original":{"line":133,"column":40}},{"generated":{"line":151,"column":51},"source":"src/Sketch.js","original":{"line":133,"column":29}},{"generated":{"line":151,"column":53},"source":"src/Sketch.js","original":{"line":133,"column":54}},{"name":"length","generated":{"line":151,"column":69},"source":"src/Sketch.js","original":{"line":133,"column":62}},{"generated":{"line":151,"column":75},"source":"src/Sketch.js","original":{"line":133,"column":54}},{"generated":{"line":151,"column":78},"source":"src/Sketch.js","original":{"line":133,"column":71}},{"generated":{"line":151,"column":79},"source":"src/Sketch.js","original":{"line":133,"column":29}},{"generated":{"line":151,"column":81},"source":"src/Sketch.js","original":{"line":133,"column":74}},{"generated":{"line":151,"column":82},"source":"src/Sketch.js","original":{"line":133,"column":29}},{"generated":{"line":151,"column":83},"source":"src/Sketch.js","original":{"line":133,"column":18}},{"generated":{"line":151,"column":84},"source":"src/Sketch.js","original":{"line":133,"column":8}},{"generated":{"line":152,"column":0},"source":"src/Sketch.js","original":{"line":134,"column":8}},{"generated":{"line":152,"column":12},"source":"src/Sketch.js","original":{"line":134,"column":12}},{"name":"i","generated":{"line":152,"column":28},"source":"src/Sketch.js","original":{"line":134,"column":20}},{"generated":{"line":152,"column":30},"source":"src/Sketch.js","original":{"line":134,"column":12}},{"name":"state","generated":{"line":152,"column":32},"source":"src/Sketch.js","original":{"line":134,"column":23}},{"generated":{"line":152,"column":37},"source":"src/Sketch.js","original":{"line":134,"column":12}},{"generated":{"line":152,"column":42},"source":"src/Sketch.js","original":{"line":134,"column":33}},{"generated":{"line":152,"column":51},"source":"src/Sketch.js","original":{"line":134,"column":8}},{"generated":{"line":152,"column":53},"source":"src/Sketch.js","original":{"line":134,"column":44}},{"generated":{"line":153,"column":0},"source":"src/Sketch.js","original":{"line":135,"column":10}},{"name":"i","generated":{"line":153,"column":26},"source":"src/Sketch.js","original":{"line":135,"column":18}},{"generated":{"line":153,"column":28},"source":"src/Sketch.js","original":{"line":135,"column":10}},{"name":"start","generated":{"line":153,"column":30},"source":"src/Sketch.js","original":{"line":135,"column":21}},{"generated":{"line":153,"column":35},"source":"src/Sketch.js","original":{"line":135,"column":10}},{"generated":{"line":154,"column":0},"source":"src/Sketch.js","original":{"line":136,"column":9}},{"generated":{"line":155,"column":0},"source":"src/Sketch.js","original":{"line":137,"column":7}},{"generated":{"line":156,"column":0},"source":"src/Sketch.js","original":{"line":139,"column":5}},{"generated":{"line":157,"column":0},"source":"src/Sketch.js","original":{"line":140,"column":3}},{"generated":{"line":157,"column":3},"source":"src/Sketch.js","original":{"line":125,"column":2}},{"generated":{"line":158,"column":0},"source":"src/Sketch.js","original":{"line":141,"column":1}},{"generated":{"line":158,"column":1},"source":"src/Sketch.js","original":{"line":124,"column":0}},{"generated":{"line":160,"column":0},"source":"src/Sketch.js","original":{"line":143,"column":0}},{"generated":{"line":161,"column":0},"source":"src/Sketch.js","original":{"line":144,"column":0}},{"name":"checkIfOverTrigger","generated":{"line":161,"column":4},"source":"src/Sketch.js","original":{"line":144,"column":6}},{"generated":{"line":161,"column":25},"source":"src/Sketch.js","original":{"line":144,"column":27}},{"name":"checkIfOverTrigger","generated":{"line":161,"column":34},"source":"src/Sketch.js","original":{"line":144,"column":6}},{"generated":{"line":161,"column":52},"source":"src/Sketch.js","original":{"line":144,"column":27}},{"name":"x","generated":{"line":161,"column":53},"source":"src/Sketch.js","original":{"line":144,"column":28}},{"generated":{"line":161,"column":54},"source":"src/Sketch.js","original":{"line":144,"column":27}},{"name":"y","generated":{"line":161,"column":56},"source":"src/Sketch.js","original":{"line":144,"column":31}},{"generated":{"line":161,"column":57},"source":"src/Sketch.js","original":{"line":144,"column":27}},{"generated":{"line":161,"column":59},"source":"src/Sketch.js","original":{"line":144,"column":37}},{"generated":{"line":162,"column":0},"source":"src/Sketch.js","original":{"line":145,"column":2}},{"name":"trigger","generated":{"line":162,"column":6},"source":"src/Sketch.js","original":{"line":145,"column":6}},{"generated":{"line":162,"column":16},"source":"src/Sketch.js","original":{"line":145,"column":16}},{"generated":{"line":162,"column":18},"source":"src/Sketch.js","original":{"line":145,"column":2}},{"name":"triggers","generated":{"line":163,"column":0},"source":"src/Sketch.js","original":{"line":146,"column":2}},{"name":"getAll","generated":{"line":163,"column":11},"source":"src/Sketch.js","original":{"line":146,"column":11}},{"generated":{"line":163,"column":17},"source":"src/Sketch.js","original":{"line":146,"column":2}},{"name":"forEach","generated":{"line":163,"column":20},"source":"src/Sketch.js","original":{"line":146,"column":20}},{"generated":{"line":163,"column":27},"source":"src/Sketch.js","original":{"line":146,"column":2}},{"generated":{"line":163,"column":28},"source":"src/Sketch.js","original":{"line":146,"column":28}},{"generated":{"line":163,"column":41},"source":"src/Sketch.js","original":{"line":146,"column":33}},{"generated":{"line":164,"column":0},"source":"src/Sketch.js","original":{"line":147,"column":4}},{"name":"x","generated":{"line":164,"column":8},"source":"src/Sketch.js","original":{"line":147,"column":8}},{"name":"t","generated":{"line":164,"column":13},"source":"src/Sketch.js","original":{"line":147,"column":13}},{"name":"x1","generated":{"line":164,"column":15},"source":"src/Sketch.js","original":{"line":147,"column":15}},{"generated":{"line":164,"column":17},"source":"src/Sketch.js","original":{"line":147,"column":8}},{"name":"x","generated":{"line":164,"column":21},"source":"src/Sketch.js","original":{"line":147,"column":21}},{"name":"t","generated":{"line":164,"column":26},"source":"src/Sketch.js","original":{"line":147,"column":26}},{"name":"x2","generated":{"line":164,"column":28},"source":"src/Sketch.js","original":{"line":147,"column":28}},{"generated":{"line":164,"column":30},"source":"src/Sketch.js","original":{"line":147,"column":8}},{"name":"y","generated":{"line":164,"column":34},"source":"src/Sketch.js","original":{"line":147,"column":34}},{"name":"t","generated":{"line":164,"column":39},"source":"src/Sketch.js","original":{"line":147,"column":39}},{"name":"y1","generated":{"line":164,"column":41},"source":"src/Sketch.js","original":{"line":147,"column":41}},{"generated":{"line":164,"column":43},"source":"src/Sketch.js","original":{"line":147,"column":8}},{"name":"y","generated":{"line":164,"column":47},"source":"src/Sketch.js","original":{"line":147,"column":47}},{"name":"t","generated":{"line":164,"column":52},"source":"src/Sketch.js","original":{"line":147,"column":52}},{"name":"y2","generated":{"line":164,"column":54},"source":"src/Sketch.js","original":{"line":147,"column":54}},{"generated":{"line":164,"column":56},"source":"src/Sketch.js","original":{"line":147,"column":4}},{"generated":{"line":164,"column":58},"source":"src/Sketch.js","original":{"line":147,"column":58}},{"name":"trigger","generated":{"line":165,"column":0},"source":"src/Sketch.js","original":{"line":148,"column":6}},{"name":"t","generated":{"line":165,"column":16},"source":"src/Sketch.js","original":{"line":148,"column":16}},{"generated":{"line":165,"column":17},"source":"src/Sketch.js","original":{"line":148,"column":6}},{"generated":{"line":166,"column":0},"source":"src/Sketch.js","original":{"line":149,"column":5}},{"generated":{"line":167,"column":0},"source":"src/Sketch.js","original":{"line":150,"column":3}},{"generated":{"line":167,"column":3},"source":"src/Sketch.js","original":{"line":146,"column":2}},{"generated":{"line":168,"column":0},"source":"src/Sketch.js","original":{"line":151,"column":2}},{"name":"trigger","generated":{"line":168,"column":9},"source":"src/Sketch.js","original":{"line":151,"column":9}},{"generated":{"line":168,"column":16},"source":"src/Sketch.js","original":{"line":151,"column":2}},{"generated":{"line":169,"column":0},"source":"src/Sketch.js","original":{"line":152,"column":1}},{"generated":{"line":169,"column":1},"source":"src/Sketch.js","original":{"line":144,"column":0}},{"generated":{"line":171,"column":0},"source":"src/Sketch.js","original":{"line":154,"column":0}},{"name":"playVideo","generated":{"line":171,"column":4},"source":"src/Sketch.js","original":{"line":154,"column":4}},{"generated":{"line":171,"column":16},"source":"src/Sketch.js","original":{"line":154,"column":16}},{"generated":{"line":171,"column":21},"source":"src/Sketch.js","original":{"line":154,"column":0}},{"generated":{"line":172,"column":0},"source":"src/Sketch.js","original":{"line":155,"column":0}},{"generated":{"line":173,"column":0},"source":"src/Sketch.js","original":{"line":156,"column":7}},{"name":"showRawVideo","generated":{"line":173,"column":4},"source":"src/Sketch.js","original":{"line":156,"column":13}},{"generated":{"line":173,"column":42},"source":"src/Sketch.js","original":{"line":156,"column":28}},{"name":"showRawVideo","generated":{"line":173,"column":51},"source":"src/Sketch.js","original":{"line":156,"column":13}},{"generated":{"line":173,"column":63},"source":"src/Sketch.js","original":{"line":156,"column":28}},{"generated":{"line":173,"column":66},"source":"src/Sketch.js","original":{"line":156,"column":34}},{"name":"playVideo","generated":{"line":174,"column":0},"source":"src/Sketch.js","original":{"line":157,"column":2}},{"generated":{"line":174,"column":14},"source":"src/Sketch.js","original":{"line":157,"column":14}},{"name":"playVideo","generated":{"line":174,"column":15},"source":"src/Sketch.js","original":{"line":157,"column":15}},{"generated":{"line":174,"column":24},"source":"src/Sketch.js","original":{"line":157,"column":2}},{"generated":{"line":175,"column":0},"source":"src/Sketch.js","original":{"line":158,"column":2}},{"name":"playVideo","generated":{"line":175,"column":6},"source":"src/Sketch.js","original":{"line":158,"column":5}},{"generated":{"line":175,"column":15},"source":"src/Sketch.js","original":{"line":158,"column":2}},{"generated":{"line":175,"column":17},"source":"src/Sketch.js","original":{"line":158,"column":15}},{"name":"capture","generated":{"line":176,"column":0},"source":"src/Sketch.js","original":{"line":159,"column":4}},{"name":"loop","generated":{"line":176,"column":12},"source":"src/Sketch.js","original":{"line":159,"column":12}},{"generated":{"line":176,"column":16},"source":"src/Sketch.js","original":{"line":159,"column":4}},{"generated":{"line":177,"column":0},"source":"src/Sketch.js","original":{"line":160,"column":3}},{"generated":{"line":177,"column":3},"source":"src/Sketch.js","original":{"line":158,"column":2}},{"generated":{"line":177,"column":9},"source":"src/Sketch.js","original":{"line":160,"column":9}},{"name":"capture","generated":{"line":178,"column":0},"source":"src/Sketch.js","original":{"line":161,"column":4}},{"name":"pause","generated":{"line":178,"column":12},"source":"src/Sketch.js","original":{"line":161,"column":12}},{"generated":{"line":178,"column":17},"source":"src/Sketch.js","original":{"line":161,"column":4}},{"generated":{"line":179,"column":0},"source":"src/Sketch.js","original":{"line":162,"column":3}},{"generated":{"line":180,"column":0},"source":"src/Sketch.js","original":{"line":163,"column":1}},{"generated":{"line":180,"column":1},"source":"src/Sketch.js","original":{"line":156,"column":7}},{"generated":{"line":182,"column":0},"source":"src/Sketch.js","original":{"line":165,"column":7}},{"name":"isTracking","generated":{"line":182,"column":4},"source":"src/Sketch.js","original":{"line":165,"column":11}},{"generated":{"line":182,"column":38},"source":"src/Sketch.js","original":{"line":165,"column":24}},{"generated":{"line":182,"column":43},"source":"src/Sketch.js","original":{"line":165,"column":7}},{"generated":{"line":183,"column":0},"source":"src/Sketch.js","original":{"line":166,"column":0}},{"generated":{"line":184,"column":0},"source":"src/Sketch.js","original":{"line":167,"column":7}},{"name":"trackVideo","generated":{"line":184,"column":4},"source":"src/Sketch.js","original":{"line":167,"column":13}},{"generated":{"line":184,"column":38},"source":"src/Sketch.js","original":{"line":167,"column":26}},{"name":"trackVideo","generated":{"line":184,"column":47},"source":"src/Sketch.js","original":{"line":167,"column":13}},{"generated":{"line":184,"column":57},"source":"src/Sketch.js","original":{"line":167,"column":26}},{"generated":{"line":184,"column":60},"source":"src/Sketch.js","original":{"line":167,"column":32}},{"generated":{"line":185,"column":0},"source":"src/Sketch.js","original":{"line":168,"column":2}},{"name":"isTracking","generated":{"line":185,"column":10},"source":"src/Sketch.js","original":{"line":165,"column":11}},{"generated":{"line":185,"column":20},"source":"src/Sketch.js","original":{"line":168,"column":2}},{"generated":{"line":185,"column":36},"source":"src/Sketch.js","original":{"line":168,"column":15}},{"name":"isTracking","generated":{"line":185,"column":37},"source":"src/Sketch.js","original":{"line":168,"column":16}},{"generated":{"line":185,"column":47},"source":"src/Sketch.js","original":{"line":168,"column":2}},{"generated":{"line":186,"column":0},"source":"src/Sketch.js","original":{"line":169,"column":2}},{"name":"isTracking","generated":{"line":186,"column":6},"source":"src/Sketch.js","original":{"line":169,"column":5}},{"generated":{"line":186,"column":16},"source":"src/Sketch.js","original":{"line":169,"column":2}},{"generated":{"line":186,"column":18},"source":"src/Sketch.js","original":{"line":169,"column":16}},{"name":"start","generated":{"line":187,"column":0},"source":"src/Sketch.js","original":{"line":170,"column":4}},{"generated":{"line":188,"column":0},"source":"src/Sketch.js","original":{"line":171,"column":3}},{"generated":{"line":189,"column":0},"source":"src/Sketch.js","original":{"line":172,"column":1}},{"generated":{"line":189,"column":1},"source":"src/Sketch.js","original":{"line":167,"column":7}},{"generated":{"line":191,"column":0},"source":"src/Sketch.js","original":{"line":174,"column":0}},{"generated":{"line":192,"column":0},"source":"src/Sketch.js","original":{"line":175,"column":0}},{"name":"start","generated":{"line":192,"column":4},"source":"src/Sketch.js","original":{"line":175,"column":6}},{"generated":{"line":192,"column":12},"source":"src/Sketch.js","original":{"line":175,"column":14}},{"name":"start","generated":{"line":192,"column":21},"source":"src/Sketch.js","original":{"line":175,"column":6}},{"generated":{"line":192,"column":26},"source":"src/Sketch.js","original":{"line":175,"column":14}},{"generated":{"line":192,"column":29},"source":"src/Sketch.js","original":{"line":175,"column":20}},{"name":"socketManager","generated":{"line":193,"column":0},"source":"src/Sketch.js","original":{"line":176,"column":2}},{"name":"sendImg","generated":{"line":193,"column":16},"source":"src/Sketch.js","original":{"line":176,"column":16}},{"generated":{"line":193,"column":23},"source":"src/Sketch.js","original":{"line":176,"column":2}},{"name":"canvas2Send","generated":{"line":193,"column":24},"source":"src/Sketch.js","original":{"line":176,"column":24}},{"name":"elt","generated":{"line":193,"column":36},"source":"src/Sketch.js","original":{"line":176,"column":36}},{"generated":{"line":193,"column":39},"source":"src/Sketch.js","original":{"line":176,"column":24}},{"name":"toDataURL","generated":{"line":193,"column":40},"source":"src/Sketch.js","original":{"line":176,"column":40}},{"generated":{"line":193,"column":49},"source":"src/Sketch.js","original":{"line":176,"column":24}},{"generated":{"line":193,"column":51},"source":"src/Sketch.js","original":{"line":176,"column":2}},{"name":"capture","generated":{"line":193,"column":53},"source":"src/Sketch.js","original":{"line":176,"column":53}},{"generated":{"line":193,"column":60},"source":"src/Sketch.js","original":{"line":176,"column":2}},{"name":"canvas2Send","generated":{"line":193,"column":62},"source":"src/Sketch.js","original":{"line":176,"column":62}},{"generated":{"line":193,"column":73},"source":"src/Sketch.js","original":{"line":176,"column":2}},{"generated":{"line":194,"column":0},"source":"src/Sketch.js","original":{"line":177,"column":1}},{"generated":{"line":194,"column":1},"source":"src/Sketch.js","original":{"line":175,"column":0}},{"generated":{"line":196,"column":0},"source":"src/Sketch.js","original":{"line":179,"column":0}},{"generated":{"line":197,"column":0},"source":"src/Sketch.js","original":{"line":180,"column":7}},{"name":"changeVideo","generated":{"line":197,"column":4},"source":"src/Sketch.js","original":{"line":180,"column":13}},{"generated":{"line":197,"column":40},"source":"src/Sketch.js","original":{"line":180,"column":27}},{"name":"changeVideo","generated":{"line":197,"column":49},"source":"src/Sketch.js","original":{"line":180,"column":13}},{"generated":{"line":197,"column":60},"source":"src/Sketch.js","original":{"line":180,"column":27}},{"generated":{"line":197,"column":63},"source":"src/Sketch.js","original":{"line":180,"column":33}},{"generated":{"line":198,"column":0},"source":"src/Sketch.js","original":{"line":181,"column":2}},{"name":"video","generated":{"line":198,"column":6},"source":"src/Sketch.js","original":{"line":181,"column":8}},{"name":"avaiVideos","generated":{"line":198,"column":14},"source":"src/Sketch.js","original":{"line":181,"column":16}},{"name":"Math","generated":{"line":198,"column":25},"source":"src/Sketch.js","original":{"line":181,"column":27}},{"name":"floor","generated":{"line":198,"column":30},"source":"src/Sketch.js","original":{"line":181,"column":32}},{"generated":{"line":198,"column":35},"source":"src/Sketch.js","original":{"line":181,"column":27}},{"name":"random","generated":{"line":198,"column":36},"source":"src/Sketch.js","original":{"line":181,"column":38}},{"generated":{"line":198,"column":43},"source":"src/Sketch.js","original":{"line":181,"column":45}},{"generated":{"line":198,"column":44},"source":"src/Sketch.js","original":{"line":181,"column":38}},{"name":"avaiVideos","generated":{"line":198,"column":46},"source":"src/Sketch.js","original":{"line":181,"column":48}},{"name":"length","generated":{"line":198,"column":57},"source":"src/Sketch.js","original":{"line":181,"column":59}},{"generated":{"line":198,"column":63},"source":"src/Sketch.js","original":{"line":181,"column":38}},{"generated":{"line":198,"column":64},"source":"src/Sketch.js","original":{"line":181,"column":27}},{"generated":{"line":198,"column":65},"source":"src/Sketch.js","original":{"line":181,"column":16}},{"generated":{"line":198,"column":66},"source":"src/Sketch.js","original":{"line":181,"column":2}},{"name":"capture","generated":{"line":199,"column":0},"source":"src/Sketch.js","original":{"line":182,"column":2}},{"name":"elt","generated":{"line":199,"column":10},"source":"src/Sketch.js","original":{"line":182,"column":10}},{"generated":{"line":199,"column":13},"source":"src/Sketch.js","original":{"line":182,"column":2}},{"name":"src","generated":{"line":199,"column":14},"source":"src/Sketch.js","original":{"line":182,"column":14}},{"generated":{"line":199,"column":17},"source":"src/Sketch.js","original":{"line":182,"column":2}},{"name":"video","generated":{"line":199,"column":20},"source":"src/Sketch.js","original":{"line":182,"column":20}},{"generated":{"line":199,"column":25},"source":"src/Sketch.js","original":{"line":182,"column":2}},{"generated":{"line":200,"column":0},"source":"src/Sketch.js","original":{"line":183,"column":1}},{"generated":{"line":200,"column":1},"source":"src/Sketch.js","original":{"line":180,"column":7}},{"generated":{"line":202,"column":0},"source":"src/Sketch.js","original":{"line":185,"column":0}},{"generated":{"line":203,"column":0},"source":"src/Sketch.js","original":{"line":186,"column":7}},{"name":"changeSound","generated":{"line":203,"column":4},"source":"src/Sketch.js","original":{"line":186,"column":13}},{"generated":{"line":203,"column":40},"source":"src/Sketch.js","original":{"line":186,"column":27}},{"name":"changeSound","generated":{"line":203,"column":49},"source":"src/Sketch.js","original":{"line":186,"column":13}},{"generated":{"line":203,"column":60},"source":"src/Sketch.js","original":{"line":186,"column":27}},{"name":"type","generated":{"line":203,"column":61},"source":"src/Sketch.js","original":{"line":186,"column":28}},{"generated":{"line":203,"column":65},"source":"src/Sketch.js","original":{"line":186,"column":27}},{"generated":{"line":203,"column":67},"source":"src/Sketch.js","original":{"line":186,"column":37}},{"name":"currentSound","generated":{"line":204,"column":0},"source":"src/Sketch.js","original":{"line":187,"column":2}},{"name":"type","generated":{"line":204,"column":17},"source":"src/Sketch.js","original":{"line":187,"column":17}},{"generated":{"line":204,"column":21},"source":"src/Sketch.js","original":{"line":187,"column":2}},{"generated":{"line":205,"column":0},"source":"src/Sketch.js","original":{"line":188,"column":1}},{"generated":{"line":205,"column":1},"source":"src/Sketch.js","original":{"line":186,"column":7}},{"name":"window","generated":{"line":207,"column":0},"source":"src/Sketch.js","original":{"line":190,"column":0}},{"name":"setup","generated":{"line":207,"column":7},"source":"src/Sketch.js","original":{"line":190,"column":7}},{"generated":{"line":207,"column":12},"source":"src/Sketch.js","original":{"line":190,"column":0}},{"name":"setup","generated":{"line":207,"column":15},"source":"src/Sketch.js","original":{"line":190,"column":15}},{"generated":{"line":207,"column":20},"source":"src/Sketch.js","original":{"line":190,"column":0}},{"name":"window","generated":{"line":208,"column":0},"source":"src/Sketch.js","original":{"line":191,"column":0}},{"name":"draw","generated":{"line":208,"column":7},"source":"src/Sketch.js","original":{"line":191,"column":7}},{"generated":{"line":208,"column":11},"source":"src/Sketch.js","original":{"line":191,"column":0}},{"name":"draw","generated":{"line":208,"column":14},"source":"src/Sketch.js","original":{"line":191,"column":14}},{"generated":{"line":208,"column":18},"source":"src/Sketch.js","original":{"line":191,"column":0}},{"name":"window","generated":{"line":209,"column":0},"source":"src/Sketch.js","original":{"line":192,"column":0}},{"name":"capture","generated":{"line":209,"column":7},"source":"src/Sketch.js","original":{"line":192,"column":7}},{"generated":{"line":209,"column":14},"source":"src/Sketch.js","original":{"line":192,"column":0}},{"name":"capture","generated":{"line":209,"column":17},"source":"src/Sketch.js","original":{"line":192,"column":17}},{"generated":{"line":209,"column":24},"source":"src/Sketch.js","original":{"line":192,"column":0}},{"name":"window","generated":{"line":210,"column":0},"source":"src/Sketch.js","original":{"line":193,"column":0}},{"name":"drawHuman","generated":{"line":210,"column":7},"source":"src/Sketch.js","original":{"line":193,"column":7}},{"generated":{"line":210,"column":16},"source":"src/Sketch.js","original":{"line":193,"column":0}},{"name":"drawHuman","generated":{"line":210,"column":19},"source":"src/Sketch.js","original":{"line":193,"column":19}},{"generated":{"line":210,"column":28},"source":"src/Sketch.js","original":{"line":193,"column":0}},{"name":"window","generated":{"line":211,"column":0},"source":"src/Sketch.js","original":{"line":194,"column":0}},{"name":"mousePressed","generated":{"line":211,"column":7},"source":"src/Sketch.js","original":{"line":194,"column":7}},{"generated":{"line":211,"column":19},"source":"src/Sketch.js","original":{"line":194,"column":0}},{"name":"mousePressed","generated":{"line":211,"column":22},"source":"src/Sketch.js","original":{"line":194,"column":22}},{"generated":{"line":211,"column":34},"source":"src/Sketch.js","original":{"line":194,"column":0}},{"name":"window","generated":{"line":212,"column":0},"source":"src/Sketch.js","original":{"line":195,"column":0}},{"name":"start","generated":{"line":212,"column":7},"source":"src/Sketch.js","original":{"line":195,"column":7}},{"generated":{"line":212,"column":12},"source":"src/Sketch.js","original":{"line":195,"column":0}},{"name":"start","generated":{"line":212,"column":15},"source":"src/Sketch.js","original":{"line":195,"column":15}},{"generated":{"line":212,"column":20},"source":"src/Sketch.js","original":{"line":195,"column":0}}],"sources":{"src/Sketch.js":"import {\n  COLORS,\n  BODY_CONNECTIONS,\n  IMAGE_WIDTH,\n  IMAGE_HEIGHT,\n  VIDEOS,\n  C_SIZE,\n  C_RADIUS,\n  FOOTER_HEIGHT\n} from './constants';\n\nimport SocketManager from './SocketManager';\nimport Triggers from './Triggers';\nimport { soundsA, soundsB } from './Player';\n\nimport video01 from './video/street01.mp4'\nimport video02 from './video/nyc.mp4'\nimport video03 from './video/street03.mp4'\n\nconst avaiVideos = [video01, video02, video03];\n\n// Current color\nlet currentColor = 'rgba(37,255,245, 0.75)';\n// Current selected sound\nlet currentSound = 'soundsA';\n\n// Circle Trigger Manager\nexport const triggers = new Triggers();\n\nlet humans = [];\nlet capture;\nlet canvas;\nlet canvas2Send;\nlet colors;\nlet socketManager;\nlet triggerTracking = false;\n\nconst setup = () => {\n  // Canvases\n  canvas = createCanvas(windowWidth, windowHeight);\n  canvas2Send = createGraphics(IMAGE_WIDTH, IMAGE_HEIGHT);\n\n  // Live Stream\n  // capture = createCapture(VIDEO);\n\n  // Video Demo\n  capture = createVideo([video02]);\n\n  // Socket Manager\n  socketManager = new SocketManager('http://localhost:33000/query', capture, canvas2Send);\n\n  capture.size(IMAGE_WIDTH, IMAGE_HEIGHT);\n  capture.hide();\n  strokeWeight(4);\n  colors = COLORS.map(e => color(e));\n  frameRate(10);\n}\n\nconst draw = () => {\n  //image(capture, 0, 0, windowWidth, windowHeight);\n  if (playVideo && !isTracking) {\n    image(capture, 0, 0, windowWidth, windowHeight);\n  }\n\n  noStroke();\n  fill(currentColor);\n\n  // Draw all triggers\n  triggers.getAll().forEach(trigger => ellipse(trigger.x, trigger.y, C_SIZE))\n\n  // Debug sounds with mouse\n  checkAndTriggerSound(mouseX, mouseY, mouseX, mouseY);\n}\n\n// Draw a human\nconst drawHuman = (human) => {\n  BODY_CONNECTIONS.forEach((connection, i) => {\n    let start = null;\n    let end = null;\n    human.forEach(bodyPart => {\n      const name = bodyPart[0];\n      if (name === connection[0]) {\n        start = bodyPart;\n      } else if (name === connection[1]) {\n        end = bodyPart;\n      }\n    });\n    stroke('rgba(87,255,245, 0.75)');\n    if (start && end) {\n      const x1 = start[1] * windowWidth;\n      const y1 = start[2] * windowHeight;\n      const x2 = end[1] * windowWidth;\n      const y2 = end[2] * windowHeight;\n\n      checkAndTriggerSound(x1, y1, x2, y2);\n      line(x1, y1, x2, y2);\n    }\n  });\n}\n\n// Add a new instrument\nconst mousePressed = () => {\n  // Check if it's on top of an existing trigger\n  const existing = checkIfOverTrigger(mouseX, mouseY);\n  if (existing.id) {\n    // Remove the existing one\n    triggers.remove(existing);\n  } else if(mouseY < windowHeight - FOOTER_HEIGHT) {\n    // Add a new trigger\n    triggers.add({\n      id: Date.now(),\n      x: mouseX,\n      y: mouseY,\n      x1: mouseX - C_RADIUS,\n      x2: mouseX + C_RADIUS,\n      y1: mouseY - C_RADIUS,\n      y2: mouseY + C_RADIUS,\n      soundType: currentSound\n    })\n  }\n}\n\n// Check if human is over a trigger\nconst checkAndTriggerSound = (x1, y1, x2, y2) => {\n  triggers.getAll().forEach(t => {\n    if (x1 >= t.x1 && x1 <= t.x2 && y1 >= t.y1 && y1 <= t.y2 || x2 >= t.x1 && x2 <= t.x2 && y2 >= t.y1 && y2 <= t.y2) {\n      if(t.soundType === 'soundsA'){\n        const i = Math.floor(map(y1, 0, windowHeight, soundsA.length - 1, 0));\n        if (soundsA[i].state === 'stopped') {\n          soundsA[i].start();\n        }\n      } else if(t.soundType === 'soundsB') {\n        const i = Math.floor(map(y1, 0, windowHeight, soundsB.length - 1, 0));\n        if (soundsB[i].state === 'stopped') {\n          soundsB[i].start();\n        }\n      }\n\n    }\n  })\n}\n\n// Check if click is over a trigger\nconst checkIfOverTrigger = (x, y) => {\n  let trigger = {};\n  triggers.getAll().forEach(t => {\n    if (x >= t.x1 && x <= t.x2 && y >= t.y1 && y <= t.y2) {\n      trigger = t;\n    }\n  });\n  return trigger;\n}\n\nlet playVideo = false;\n// Show the raw video stream\nexport const showRawVideo = () => {\n  playVideo = !playVideo;\n  if(playVideo){\n    capture.loop()\n  } else {\n    capture.pause();\n  }\n}\n\nexport let isTracking = false;\n// Start Tracking the current video\nexport const trackVideo = () => {\n  isTracking = !isTracking;\n  if(isTracking){\n    start()\n  }  \n}\n\n// Log start\nconst start = () => {\n  socketManager.sendImg(canvas2Send.elt.toDataURL(), capture, canvas2Send);\n}\n\n// Change the video src\nexport const changeVideo = () => {\n  const video = avaiVideos[Math.floor(random(0, avaiVideos.length))];\n  capture.elt.src = video;\n}\n\n// Change the sound and color\nexport const changeSound = (type) => {\n  currentSound = type;\n}\n\nwindow.setup = setup;\nwindow.draw = draw;\nwindow.capture = capture;\nwindow.drawHuman = drawHuman;\nwindow.mousePressed = mousePressed;\nwindow.start = start;"},"lineCount":null}},"hash":"8ac474042703dbe3705afe3bb0f52836","cacheData":{"env":{}}}