{"dependencies":[{"name":"/Users/cristobalvalenzuela/dropbox/itp/spring2018/interactivemusic/work/sidewalk/.babelrc","includedInParent":true,"mtime":1520315592761},{"name":"/Users/cristobalvalenzuela/dropbox/itp/spring2018/interactivemusic/work/sidewalk/package.json","includedInParent":true,"mtime":1520326924636},{"name":"React","loc":{"line":1,"column":18}},{"name":"react-dom","loc":{"line":2,"column":21}},{"name":"./UI","loc":{"line":3,"column":15}},{"name":"./Sketch","loc":{"line":12,"column":7}},{"name":"./styles/reset.css","loc":{"line":13,"column":7}},{"name":"./styles/index.css","loc":{"line":14,"column":7}}],"generated":{"js":"'use strict';\n\nvar _React = require('React');\n\nvar _React2 = _interopRequireDefault(_React);\n\nvar _reactDom = require('react-dom');\n\nvar _reactDom2 = _interopRequireDefault(_reactDom);\n\nvar _UI = require('./UI');\n\nvar _UI2 = _interopRequireDefault(_UI);\n\nvar _Sketch = require('./Sketch');\n\nrequire('./styles/reset.css');\n\nrequire('./styles/index.css');\n\nfunction _interopRequireDefault(obj) { return obj && obj.__esModule ? obj : { default: obj }; }\n\n_reactDom2.default.render(_React2.default.createElement(_UI2.default, {\n  showVideo: _Sketch.showRawVideo,\n  startTracking: _Sketch.trackVideo,\n  triggers: _Sketch.triggers,\n  changeVideo: _Sketch.changeVideo\n}), document.getElementById('react-ui'));","map":{"mappings":[{"generated":{"line":3,"column":0},"source":"src/index.js","original":{"line":1,"column":0}},{"generated":{"line":7,"column":0},"source":"src/index.js","original":{"line":2,"column":0}},{"generated":{"line":11,"column":0},"source":"src/index.js","original":{"line":3,"column":0}},{"generated":{"line":15,"column":0},"source":"src/index.js","original":{"line":5,"column":0}},{"generated":{"line":17,"column":0},"source":"src/index.js","original":{"line":13,"column":0}},{"generated":{"line":19,"column":0},"source":"src/index.js","original":{"line":14,"column":0}},{"generated":{"line":23,"column":0},"source":"src/index.js","original":{"line":16,"column":0}},{"name":"render","generated":{"line":23,"column":19},"source":"src/index.js","original":{"line":16,"column":9}},{"generated":{"line":23,"column":25},"source":"src/index.js","original":{"line":16,"column":0}},{"generated":{"line":23,"column":26},"source":"src/index.js","original":{"line":17,"column":2}},{"generated":{"line":24,"column":0},"source":"src/index.js","original":{"line":18,"column":4}},{"generated":{"line":24,"column":33},"source":"src/index.js","original":{"line":17,"column":2}},{"generated":{"line":25,"column":0},"source":"src/index.js","original":{"line":19,"column":4}},{"generated":{"line":25,"column":35},"source":"src/index.js","original":{"line":17,"column":2}},{"generated":{"line":26,"column":0},"source":"src/index.js","original":{"line":20,"column":4}},{"generated":{"line":26,"column":28},"source":"src/index.js","original":{"line":17,"column":2}},{"generated":{"line":27,"column":0},"source":"src/index.js","original":{"line":21,"column":4}},{"generated":{"line":28,"column":0},"source":"src/index.js","original":{"line":17,"column":2}},{"generated":{"line":28,"column":2},"source":"src/index.js","original":{"line":16,"column":0}},{"name":"document","generated":{"line":28,"column":4},"source":"src/index.js","original":{"line":23,"column":4}},{"name":"getElementById","generated":{"line":28,"column":13},"source":"src/index.js","original":{"line":23,"column":13}},{"generated":{"line":28,"column":27},"source":"src/index.js","original":{"line":23,"column":4}},{"generated":{"line":28,"column":28},"source":"src/index.js","original":{"line":23,"column":28}},{"generated":{"line":28,"column":38},"source":"src/index.js","original":{"line":23,"column":4}},{"generated":{"line":28,"column":39},"source":"src/index.js","original":{"line":16,"column":0}}],"sources":{"src/index.js":"import React from 'React';\nimport ReactDOM from 'react-dom';\nimport UI from './UI';\n\nimport {\n  showRawVideo,\n  trackVideo,\n  triggers,\n  changeVideo\n} from './Sketch';\n\nimport './Sketch';\nimport './styles/reset.css';\nimport './styles/index.css';\n\nReactDOM.render(\n  <UI \n    showVideo={showRawVideo}\n    startTracking={trackVideo}\n    triggers={triggers}\n    changeVideo={changeVideo}\n  />\n  , document.getElementById('react-ui'));"},"lineCount":null}},"hash":"48061650b115a9bf71a61ca82ac554df","cacheData":{"env":{}}}