{"dependencies":[{"name":"/Users/cristobalvalenzuela/dropbox/itp/spring2018/interactivemusic/work/sidewalk/.babelrc","includedInParent":true,"mtime":1520315592761},{"name":"/Users/cristobalvalenzuela/dropbox/itp/spring2018/interactivemusic/work/sidewalk/package.json","includedInParent":true,"mtime":1520326924636}],"generated":{"js":"'use strict';\n\nObject.defineProperty(exports, \"__esModule\", {\n  value: true\n});\nvar IMAGE_WIDTH = 432;\nvar IMAGE_HEIGHT = 368;\n\nvar VIDEOS = {\n  s1: 'https://dl.dropbox.com/s/opd7cqrkfpjuog1/street01.mp4?dl=0',\n  s2: 'https://dl.dropbox.com/s/5iqookf3lj4i1zp/street02.mp4?dl=0'\n};\n\nvar BODY_CONNECTIONS = [['Nose', 'Left_Eye'], ['Left_Eye', 'Left_Ear'], ['Nose', 'Right_Eye'], ['Right_Eye', 'Right_Ear'], ['Nose', 'Neck'], ['Neck', 'Right_Shoulder'], ['Right_Shoulder', 'Right_Elbow'], ['Right_Elbow', 'Right_Wrist'], ['Neck', 'Left_Shoulder'], ['Left_Shoulder', 'Left_Elbow'], ['Left_Elbow', 'Left_Wrist'], ['Neck', 'Right_Hip'], ['Right_Hip', 'Right_Knee'], ['Right_Knee', 'Right_Ankle'], ['Neck', 'Left_Hip'], ['Left_Hip', 'Left_Knee'], ['Left_Knee', 'Left_Ankle']];\n\nvar COLORS = ['#00ff00', '#ffff00', '#ff0000', '#00ffff', '#ffffff', '#f4f', '#00ff', '#ffaf00', '#aff', '#aaf', '#33a', '#55f', '#771', '#15f', '#ff0000', '#00ff00', '#ffff00', '#ff0000'];\n\nexports.BODY_CONNECTIONS = BODY_CONNECTIONS;\nexports.COLORS = COLORS;\nexports.IMAGE_WIDTH = IMAGE_WIDTH;\nexports.IMAGE_HEIGHT = IMAGE_HEIGHT;\nexports.VIDEOS = VIDEOS;","map":{"mappings":[{"generated":{"line":6,"column":0},"source":"src/constants.js","original":{"line":1,"column":0}},{"name":"IMAGE_WIDTH","generated":{"line":6,"column":4},"source":"src/constants.js","original":{"line":1,"column":6}},{"generated":{"line":6,"column":18},"source":"src/constants.js","original":{"line":1,"column":20}},{"generated":{"line":6,"column":21},"source":"src/constants.js","original":{"line":1,"column":0}},{"generated":{"line":7,"column":0},"source":"src/constants.js","original":{"line":2,"column":0}},{"name":"IMAGE_HEIGHT","generated":{"line":7,"column":4},"source":"src/constants.js","original":{"line":2,"column":6}},{"generated":{"line":7,"column":19},"source":"src/constants.js","original":{"line":2,"column":21}},{"generated":{"line":7,"column":22},"source":"src/constants.js","original":{"line":2,"column":0}},{"generated":{"line":9,"column":0},"source":"src/constants.js","original":{"line":4,"column":0}},{"name":"VIDEOS","generated":{"line":9,"column":4},"source":"src/constants.js","original":{"line":4,"column":6}},{"generated":{"line":9,"column":13},"source":"src/constants.js","original":{"line":4,"column":15}},{"name":"s1","generated":{"line":10,"column":0},"source":"src/constants.js","original":{"line":5,"column":2}},{"generated":{"line":10,"column":6},"source":"src/constants.js","original":{"line":5,"column":6}},{"generated":{"line":10,"column":66},"source":"src/constants.js","original":{"line":4,"column":15}},{"name":"s2","generated":{"line":11,"column":0},"source":"src/constants.js","original":{"line":6,"column":2}},{"generated":{"line":11,"column":6},"source":"src/constants.js","original":{"line":6,"column":6}},{"generated":{"line":12,"column":0},"source":"src/constants.js","original":{"line":4,"column":15}},{"generated":{"line":12,"column":1},"source":"src/constants.js","original":{"line":4,"column":0}},{"generated":{"line":14,"column":0},"source":"src/constants.js","original":{"line":9,"column":0}},{"name":"BODY_CONNECTIONS","generated":{"line":14,"column":4},"source":"src/constants.js","original":{"line":9,"column":6}},{"generated":{"line":14,"column":23},"source":"src/constants.js","original":{"line":9,"column":25}},{"generated":{"line":14,"column":24},"source":"src/constants.js","original":{"line":10,"column":2}},{"generated":{"line":14,"column":25},"source":"src/constants.js","original":{"line":10,"column":3}},{"generated":{"line":14,"column":31},"source":"src/constants.js","original":{"line":10,"column":2}},{"generated":{"line":14,"column":33},"source":"src/constants.js","original":{"line":10,"column":11}},{"generated":{"line":14,"column":43},"source":"src/constants.js","original":{"line":10,"column":2}},{"generated":{"line":14,"column":44},"source":"src/constants.js","original":{"line":9,"column":25}},{"generated":{"line":14,"column":46},"source":"src/constants.js","original":{"line":11,"column":2}},{"generated":{"line":14,"column":47},"source":"src/constants.js","original":{"line":11,"column":3}},{"generated":{"line":14,"column":57},"source":"src/constants.js","original":{"line":11,"column":2}},{"generated":{"line":14,"column":59},"source":"src/constants.js","original":{"line":11,"column":15}},{"generated":{"line":14,"column":69},"source":"src/constants.js","original":{"line":11,"column":2}},{"generated":{"line":14,"column":70},"source":"src/constants.js","original":{"line":9,"column":25}},{"generated":{"line":14,"column":72},"source":"src/constants.js","original":{"line":12,"column":2}},{"generated":{"line":14,"column":73},"source":"src/constants.js","original":{"line":12,"column":3}},{"generated":{"line":14,"column":79},"source":"src/constants.js","original":{"line":12,"column":2}},{"generated":{"line":14,"column":81},"source":"src/constants.js","original":{"line":12,"column":11}},{"generated":{"line":14,"column":92},"source":"src/constants.js","original":{"line":12,"column":2}},{"generated":{"line":14,"column":93},"source":"src/constants.js","original":{"line":9,"column":25}},{"generated":{"line":14,"column":95},"source":"src/constants.js","original":{"line":13,"column":2}},{"generated":{"line":14,"column":96},"source":"src/constants.js","original":{"line":13,"column":3}},{"generated":{"line":14,"column":107},"source":"src/constants.js","original":{"line":13,"column":2}},{"generated":{"line":14,"column":109},"source":"src/constants.js","original":{"line":13,"column":16}},{"generated":{"line":14,"column":120},"source":"src/constants.js","original":{"line":13,"column":2}},{"generated":{"line":14,"column":121},"source":"src/constants.js","original":{"line":9,"column":25}},{"generated":{"line":14,"column":123},"source":"src/constants.js","original":{"line":14,"column":2}},{"generated":{"line":14,"column":124},"source":"src/constants.js","original":{"line":14,"column":3}},{"generated":{"line":14,"column":130},"source":"src/constants.js","original":{"line":14,"column":2}},{"generated":{"line":14,"column":132},"source":"src/constants.js","original":{"line":14,"column":11}},{"generated":{"line":14,"column":138},"source":"src/constants.js","original":{"line":14,"column":2}},{"generated":{"line":14,"column":139},"source":"src/constants.js","original":{"line":9,"column":25}},{"generated":{"line":14,"column":141},"source":"src/constants.js","original":{"line":15,"column":2}},{"generated":{"line":14,"column":142},"source":"src/constants.js","original":{"line":15,"column":3}},{"generated":{"line":14,"column":148},"source":"src/constants.js","original":{"line":15,"column":2}},{"generated":{"line":14,"column":150},"source":"src/constants.js","original":{"line":15,"column":11}},{"generated":{"line":14,"column":166},"source":"src/constants.js","original":{"line":15,"column":2}},{"generated":{"line":14,"column":167},"source":"src/constants.js","original":{"line":9,"column":25}},{"generated":{"line":14,"column":169},"source":"src/constants.js","original":{"line":16,"column":2}},{"generated":{"line":14,"column":170},"source":"src/constants.js","original":{"line":16,"column":3}},{"generated":{"line":14,"column":186},"source":"src/constants.js","original":{"line":16,"column":2}},{"generated":{"line":14,"column":188},"source":"src/constants.js","original":{"line":16,"column":21}},{"generated":{"line":14,"column":201},"source":"src/constants.js","original":{"line":16,"column":2}},{"generated":{"line":14,"column":202},"source":"src/constants.js","original":{"line":9,"column":25}},{"generated":{"line":14,"column":204},"source":"src/constants.js","original":{"line":17,"column":2}},{"generated":{"line":14,"column":205},"source":"src/constants.js","original":{"line":17,"column":3}},{"generated":{"line":14,"column":218},"source":"src/constants.js","original":{"line":17,"column":2}},{"generated":{"line":14,"column":220},"source":"src/constants.js","original":{"line":17,"column":18}},{"generated":{"line":14,"column":233},"source":"src/constants.js","original":{"line":17,"column":2}},{"generated":{"line":14,"column":234},"source":"src/constants.js","original":{"line":9,"column":25}},{"generated":{"line":14,"column":236},"source":"src/constants.js","original":{"line":18,"column":2}},{"generated":{"line":14,"column":237},"source":"src/constants.js","original":{"line":18,"column":3}},{"generated":{"line":14,"column":243},"source":"src/constants.js","original":{"line":18,"column":2}},{"generated":{"line":14,"column":245},"source":"src/constants.js","original":{"line":18,"column":11}},{"generated":{"line":14,"column":260},"source":"src/constants.js","original":{"line":18,"column":2}},{"generated":{"line":14,"column":261},"source":"src/constants.js","original":{"line":9,"column":25}},{"generated":{"line":14,"column":263},"source":"src/constants.js","original":{"line":19,"column":2}},{"generated":{"line":14,"column":264},"source":"src/constants.js","original":{"line":19,"column":3}},{"generated":{"line":14,"column":279},"source":"src/constants.js","original":{"line":19,"column":2}},{"generated":{"line":14,"column":281},"source":"src/constants.js","original":{"line":19,"column":20}},{"generated":{"line":14,"column":293},"source":"src/constants.js","original":{"line":19,"column":2}},{"generated":{"line":14,"column":294},"source":"src/constants.js","original":{"line":9,"column":25}},{"generated":{"line":14,"column":296},"source":"src/constants.js","original":{"line":20,"column":2}},{"generated":{"line":14,"column":297},"source":"src/constants.js","original":{"line":20,"column":3}},{"generated":{"line":14,"column":309},"source":"src/constants.js","original":{"line":20,"column":2}},{"generated":{"line":14,"column":311},"source":"src/constants.js","original":{"line":20,"column":17}},{"generated":{"line":14,"column":323},"source":"src/constants.js","original":{"line":20,"column":2}},{"generated":{"line":14,"column":324},"source":"src/constants.js","original":{"line":9,"column":25}},{"generated":{"line":14,"column":326},"source":"src/constants.js","original":{"line":21,"column":2}},{"generated":{"line":14,"column":327},"source":"src/constants.js","original":{"line":21,"column":3}},{"generated":{"line":14,"column":333},"source":"src/constants.js","original":{"line":21,"column":2}},{"generated":{"line":14,"column":335},"source":"src/constants.js","original":{"line":21,"column":11}},{"generated":{"line":14,"column":346},"source":"src/constants.js","original":{"line":21,"column":2}},{"generated":{"line":14,"column":347},"source":"src/constants.js","original":{"line":9,"column":25}},{"generated":{"line":14,"column":349},"source":"src/constants.js","original":{"line":22,"column":2}},{"generated":{"line":14,"column":350},"source":"src/constants.js","original":{"line":22,"column":3}},{"generated":{"line":14,"column":361},"source":"src/constants.js","original":{"line":22,"column":2}},{"generated":{"line":14,"column":363},"source":"src/constants.js","original":{"line":22,"column":16}},{"generated":{"line":14,"column":375},"source":"src/constants.js","original":{"line":22,"column":2}},{"generated":{"line":14,"column":376},"source":"src/constants.js","original":{"line":9,"column":25}},{"generated":{"line":14,"column":378},"source":"src/constants.js","original":{"line":23,"column":2}},{"generated":{"line":14,"column":379},"source":"src/constants.js","original":{"line":23,"column":3}},{"generated":{"line":14,"column":391},"source":"src/constants.js","original":{"line":23,"column":2}},{"generated":{"line":14,"column":393},"source":"src/constants.js","original":{"line":23,"column":17}},{"generated":{"line":14,"column":406},"source":"src/constants.js","original":{"line":23,"column":2}},{"generated":{"line":14,"column":407},"source":"src/constants.js","original":{"line":9,"column":25}},{"generated":{"line":14,"column":409},"source":"src/constants.js","original":{"line":24,"column":2}},{"generated":{"line":14,"column":410},"source":"src/constants.js","original":{"line":24,"column":3}},{"generated":{"line":14,"column":416},"source":"src/constants.js","original":{"line":24,"column":2}},{"generated":{"line":14,"column":418},"source":"src/constants.js","original":{"line":24,"column":11}},{"generated":{"line":14,"column":428},"source":"src/constants.js","original":{"line":24,"column":2}},{"generated":{"line":14,"column":429},"source":"src/constants.js","original":{"line":9,"column":25}},{"generated":{"line":14,"column":431},"source":"src/constants.js","original":{"line":25,"column":2}},{"generated":{"line":14,"column":432},"source":"src/constants.js","original":{"line":25,"column":3}},{"generated":{"line":14,"column":442},"source":"src/constants.js","original":{"line":25,"column":2}},{"generated":{"line":14,"column":444},"source":"src/constants.js","original":{"line":25,"column":15}},{"generated":{"line":14,"column":455},"source":"src/constants.js","original":{"line":25,"column":2}},{"generated":{"line":14,"column":456},"source":"src/constants.js","original":{"line":9,"column":25}},{"generated":{"line":14,"column":458},"source":"src/constants.js","original":{"line":26,"column":2}},{"generated":{"line":14,"column":459},"source":"src/constants.js","original":{"line":26,"column":3}},{"generated":{"line":14,"column":470},"source":"src/constants.js","original":{"line":26,"column":2}},{"generated":{"line":14,"column":472},"source":"src/constants.js","original":{"line":26,"column":16}},{"generated":{"line":14,"column":484},"source":"src/constants.js","original":{"line":26,"column":2}},{"generated":{"line":14,"column":485},"source":"src/constants.js","original":{"line":9,"column":25}},{"generated":{"line":14,"column":486},"source":"src/constants.js","original":{"line":9,"column":0}},{"generated":{"line":16,"column":0},"source":"src/constants.js","original":{"line":29,"column":0}},{"name":"COLORS","generated":{"line":16,"column":4},"source":"src/constants.js","original":{"line":29,"column":6}},{"generated":{"line":16,"column":13},"source":"src/constants.js","original":{"line":29,"column":15}},{"generated":{"line":16,"column":14},"source":"src/constants.js","original":{"line":30,"column":2}},{"generated":{"line":16,"column":23},"source":"src/constants.js","original":{"line":29,"column":15}},{"generated":{"line":16,"column":25},"source":"src/constants.js","original":{"line":31,"column":2}},{"generated":{"line":16,"column":34},"source":"src/constants.js","original":{"line":29,"column":15}},{"generated":{"line":16,"column":36},"source":"src/constants.js","original":{"line":32,"column":2}},{"generated":{"line":16,"column":45},"source":"src/constants.js","original":{"line":29,"column":15}},{"generated":{"line":16,"column":47},"source":"src/constants.js","original":{"line":33,"column":2}},{"generated":{"line":16,"column":56},"source":"src/constants.js","original":{"line":29,"column":15}},{"generated":{"line":16,"column":58},"source":"src/constants.js","original":{"line":34,"column":2}},{"generated":{"line":16,"column":67},"source":"src/constants.js","original":{"line":29,"column":15}},{"generated":{"line":16,"column":69},"source":"src/constants.js","original":{"line":35,"column":2}},{"generated":{"line":16,"column":75},"source":"src/constants.js","original":{"line":29,"column":15}},{"generated":{"line":16,"column":77},"source":"src/constants.js","original":{"line":36,"column":2}},{"generated":{"line":16,"column":84},"source":"src/constants.js","original":{"line":29,"column":15}},{"generated":{"line":16,"column":86},"source":"src/constants.js","original":{"line":37,"column":2}},{"generated":{"line":16,"column":95},"source":"src/constants.js","original":{"line":29,"column":15}},{"generated":{"line":16,"column":97},"source":"src/constants.js","original":{"line":38,"column":2}},{"generated":{"line":16,"column":103},"source":"src/constants.js","original":{"line":29,"column":15}},{"generated":{"line":16,"column":105},"source":"src/constants.js","original":{"line":39,"column":2}},{"generated":{"line":16,"column":111},"source":"src/constants.js","original":{"line":29,"column":15}},{"generated":{"line":16,"column":113},"source":"src/constants.js","original":{"line":40,"column":2}},{"generated":{"line":16,"column":119},"source":"src/constants.js","original":{"line":29,"column":15}},{"generated":{"line":16,"column":121},"source":"src/constants.js","original":{"line":41,"column":2}},{"generated":{"line":16,"column":127},"source":"src/constants.js","original":{"line":29,"column":15}},{"generated":{"line":16,"column":129},"source":"src/constants.js","original":{"line":42,"column":2}},{"generated":{"line":16,"column":135},"source":"src/constants.js","original":{"line":29,"column":15}},{"generated":{"line":16,"column":137},"source":"src/constants.js","original":{"line":43,"column":2}},{"generated":{"line":16,"column":143},"source":"src/constants.js","original":{"line":29,"column":15}},{"generated":{"line":16,"column":145},"source":"src/constants.js","original":{"line":44,"column":2}},{"generated":{"line":16,"column":154},"source":"src/constants.js","original":{"line":29,"column":15}},{"generated":{"line":16,"column":156},"source":"src/constants.js","original":{"line":45,"column":2}},{"generated":{"line":16,"column":165},"source":"src/constants.js","original":{"line":29,"column":15}},{"generated":{"line":16,"column":167},"source":"src/constants.js","original":{"line":46,"column":2}},{"generated":{"line":16,"column":176},"source":"src/constants.js","original":{"line":29,"column":15}},{"generated":{"line":16,"column":178},"source":"src/constants.js","original":{"line":47,"column":2}},{"generated":{"line":16,"column":187},"source":"src/constants.js","original":{"line":29,"column":15}},{"generated":{"line":16,"column":188},"source":"src/constants.js","original":{"line":29,"column":0}},{"name":"BODY_CONNECTIONS","generated":{"line":18,"column":8},"source":"src/constants.js","original":{"line":51,"column":2}},{"name":"BODY_CONNECTIONS","generated":{"line":18,"column":27},"source":"src/constants.js","original":{"line":51,"column":2}},{"name":"COLORS","generated":{"line":19,"column":8},"source":"src/constants.js","original":{"line":52,"column":2}},{"name":"COLORS","generated":{"line":19,"column":17},"source":"src/constants.js","original":{"line":52,"column":2}},{"name":"IMAGE_WIDTH","generated":{"line":20,"column":8},"source":"src/constants.js","original":{"line":53,"column":2}},{"name":"IMAGE_WIDTH","generated":{"line":20,"column":22},"source":"src/constants.js","original":{"line":53,"column":2}},{"name":"IMAGE_HEIGHT","generated":{"line":21,"column":8},"source":"src/constants.js","original":{"line":54,"column":2}},{"name":"IMAGE_HEIGHT","generated":{"line":21,"column":23},"source":"src/constants.js","original":{"line":54,"column":2}},{"name":"VIDEOS","generated":{"line":22,"column":8},"source":"src/constants.js","original":{"line":55,"column":2}},{"name":"VIDEOS","generated":{"line":22,"column":17},"source":"src/constants.js","original":{"line":55,"column":2}}],"sources":{"src/constants.js":"const IMAGE_WIDTH = 432;\nconst IMAGE_HEIGHT = 368;\n\nconst VIDEOS = {\n  s1: 'https://dl.dropbox.com/s/opd7cqrkfpjuog1/street01.mp4?dl=0',\n  s2: 'https://dl.dropbox.com/s/5iqookf3lj4i1zp/street02.mp4?dl=0'\n}\n\nconst BODY_CONNECTIONS = [\n  ['Nose', 'Left_Eye'],\n  ['Left_Eye', 'Left_Ear'],\n  ['Nose', 'Right_Eye'],\n  ['Right_Eye', 'Right_Ear'],\n  ['Nose', 'Neck'],\n  ['Neck', 'Right_Shoulder'],\n  ['Right_Shoulder', 'Right_Elbow'],\n  ['Right_Elbow', 'Right_Wrist'],\n  ['Neck', 'Left_Shoulder'],\n  ['Left_Shoulder', 'Left_Elbow'],\n  ['Left_Elbow', 'Left_Wrist'],\n  ['Neck', 'Right_Hip'],\n  ['Right_Hip', 'Right_Knee'],\n  ['Right_Knee', 'Right_Ankle'],\n  ['Neck', 'Left_Hip'],\n  ['Left_Hip', 'Left_Knee'],\n  ['Left_Knee', 'Left_Ankle'],\n]\n\nconst COLORS = [\n  '#00ff00',\n  '#ffff00',\n  '#ff0000',\n  '#00ffff',\n  '#ffffff',\n  '#f4f',\n  '#00ff',\n  '#ffaf00',\n  '#aff',\n  '#aaf',\n  '#33a',\n  '#55f',\n  '#771',\n  '#15f',\n  '#ff0000',\n  '#00ff00',\n  '#ffff00',\n  '#ff0000'\n]\n\nexport {\n  BODY_CONNECTIONS,\n  COLORS,\n  IMAGE_WIDTH,\n  IMAGE_HEIGHT,\n  VIDEOS\n}"},"lineCount":null}},"hash":"de42c4054c9e45a6ac4428f5bb9b0b95","cacheData":{"env":{}}}